Workbook

Sheet NOMINAS_ACTIVAS
A5: 80185
A6: 205737
A7: 206105
A8: 20985
A9: 5055
A10: 206295
A11: 206297
A12: 206252
A13: 6325
A14: 206309
A15: 206310
A16: 206317
... A81: 5098
A82: 206338
A83: 427
A84: 6058
A85: 5913
A86: 6283
A87: 555
A88: 205454
A89: 5803
A90: 5949
A91: 303
A92: 5537
A93: 6218
A94: 5352
... A346: 3974
A347: 2027
A348: 3970
A349: 2028
A350: 1997
A351: 3973
A352: 3979
A353: 3990
A354: 2029
A355: 3897
A356: 2030
A357: 2019
A358: 2023
A359: 3967
... A693: 62019

Sheet  PLAN Y PROGRAMA ANUAL 2026
T3: Gerencia Metropolitana Norte
T4: Subgerencia de Administración y Finanzas
T5: Departamento de Relaciones Industriales
T6: Capacitación, Adiestramiento y Productividad
A13: COMISION MIXTA DE CAPACITACIÓN, ADIESTRAMIENTO Y PRODUCTIVIDAD
A14: PERIODO: 01 DE ENERO AL 31 DE DICIEMBRE DEL 2026
A15: PLAN Y PROGRAMA DE CAPACITACIÓN, ADIESTRAMIENTO Y PRODUCTIVIDAD / FORMATO DC-2
A17: NO | B17: CENTRO DE COSTOS | C17: PUESTO | D17: NÓMINA | E17: NOMBRE DEL TRABAJADOR | F17: ÁREA | G17: CURP | H17: INDUCCIÓN | I17: Columna1 | J17: Columna2 | K17: CAPACITACIÒN | L17: Columna3 | M17: Columna4 | N17: MODALIDAD DEL CURSO | O17: NOMBRE DEL CURSO | P17: FI | Q17: FT | R17: D | S17: GÉNERO | T17: C/S COSTO | U17: TOTAL DE HORAS
H18: FI | I18: FT | J18: D | K18: FI | L18: FT | M18: D
A19: 1 | B19: 301 | C19: GERENTE | D19: 80185 | E19: MARCO ANTONIO VILCHIS LARA | F19: GERENCIA | G19: VILM820421HDFLRR03 | S19: H | U19: =SUM(' PLAN Y PROGRAMA ANUAL 2026'!$R19:$R19) -> 0
A20: {=IF(B20<>"",COUNTIF($B$19:B20,"<>"),"")} -> 2 | B20: 301 | C20: JEFE DE OFICINA | D20: 205737 | E20: ESQUIVEL DE LA CRUZ ESTHELA | F20: GERENCIA | G20: EUCE641228MMCSRS01 | S20: M | T20: =IFERROR(VLOOKUP(O20, '[1]CURSOS 2025'!A:B, 2, FALSE), "") | U20: =SUM(' PLAN Y PROGRAMA ANUAL 2026'!$R20:$R20) -> 0
A21: {=IF(B21<>"",COUNTIF($B$19:B21,"<>"),"")} -> 3 | B21: 301 | C21: JEFE DE UNIDAD | D21: 206786 | E21: BAEZ BRENES ALICIA MICHEL | F21: GERENCIA | G21: BABA000128MMCZRLA6 | S21: M | T21: =IFERROR(VLOOKUP(O21, '[1]CURSOS 2025'!A:B, 2, FALSE), "") | U21: =SUM(' PLAN Y PROGRAMA ANUAL 2026'!$R21) -> 0
A22: {=IF(B22<>"",COUNTIF($B$19:B22,"<>"),"")} -> 4 | B22: 317 | C22: COORDINADOR GENERAL | D22: 20985 | E22: SUAREZ RODRÍGUEZ MARINO | F22: GERENCIA | G22: SURM691226HVZRDR02 | K22: X | L22: X | M22: X | N22: EN LINEA | O22: ACCIONES PARA ABORDAR RIESGOS Y OPORTUNIDADES | P22: 46069 | Q22: 46069 | R22: 2 | S22: H | T22: S/COSTO | U22: =SUM(R22:R25) -> 8
A23: {=IF(B23<>"",COUNTIF($B$19:B23,"<>"),"")} | K23: X | L23: X | M23: X | N23: EN LINEA | O23: ISO 9001 : 2026 Y SUS NUEVOS REQUERIMENTOS | P23: 46071 | Q23: 46071 | R23: 2 | S23: H | T23: S/COSTO
A24: {=IF(B24<>"",COUNTIF($B$19:B24,"<>"),"")} | K24: X | L24: X | M24: X | N24: EN LINEA | O24: CONTROL DE LA INFORMACIÓN DOCUMENTADA | P24: 46071 | Q24: 46071 | R24: 2 | S24: H | T24: S/COSTO
A25: {=IF(B25<>"",COUNTIF($B$19:B25,"<>"),"")} | K25: X | L25: X | M25: X | N25: EN LINEA | O25: CUMPLIMIENTO DEL REQUISITO CALIBRACIÓN DE INSTRUMENTOS DE MEDICIÓN | P25: 46073 | Q25: 46073 | R25: 2 | S25: H | T25: S/COSTO
A26: {=IF(B26<>"",COUNTIF($B$19:B26,"<>"),"")}
A27: {=IF(B27<>"",COUNTIF($B$19:B27,"<>"),"")} -> 5 | B27: 317 | C27: AUXILIAR ADMINISTRATIVO | D27: 206252 | E27: MORA SÁNCHEZ CARLA ANDREA | F27: DEPARTAMENTO DE CONTROL DE CALIDAD | G27: MOSC951225MDFRNR02 | S27: M | U27: =SUM(' PLAN Y PROGRAMA ANUAL 2026'!$R27:$R27) -> 0
A28: {=IF(B28<>"",COUNTIF($B$19:B28,"<>"),"")} -> 6 | B28: 317 | C28: QUIMICO | D28: 206105 | E28: LÓPEZ HERNÁNDEZ MARISOL | F28: DEPARTAMENTO DE CONTROL DE CALIDAD | G28: LOHM830715MSLPRR01 | K28: X | L28: X | M28: X | N28: EN LINEA | O28: ACCIONES PARA ABORDAR RIESGOS Y OPORTUNIDADES | P28: 46069 | Q28: 46069 | R28: 2 | S28: M | T28: S/COSTO | U28: =SUM(' PLAN Y PROGRAMA ANUAL 2026'!$R28:$R30) -> 6
A29: {=IF(B29<>"",COUNTIF($B$19:B29,"<>"),"")} | K29: X | L29: X | M29: X | N29: EN LINEA | O29: ISO 9001 : 2026 Y SUS NUEVOS REQUERIMENTOS | P29: 46071 | Q29: 46071 | R29: 2 | S29: M | T29: S/COSTO
A30: {=IF(B30<>"",COUNTIF($B$19:B30,"<>"),"")} | K30: X | L30: X | M30: X | N30: EN LINEA | O30: CUMPLIMIENTO DEL REQUISITO CALIBRACIÓN DE INSTRUMENTOS DE MEDICIÓN | P30: 46073 | Q30: 46073 | R30: 2 | S30: M | T30: S/COSTO
A31: {=IF(B31<>"",COUNTIF($B$19:B31,"<>"),"")} -> 7 | B31: 317 | C31: TECNICO QUÍMICO | D31: 206108 | E31: RANGEL DÍAZ RAUL | F31: DEPARTAMENTO DE CONTROL DE CALIDAD | G31: RADR640901HDFNZL05 | S31: H | T31: =IFERROR(VLOOKUP(O31, '[1]CURSOS 2025'!A:B, 2, FALSE), "") | U31: =SUM(' PLAN Y PROGRAMA ANUAL 2026'!$R31:$R31) -> 0
A32: {=IF(B32<>"",COUNTIF($B$19:B32,"<>"),"")} -> 8 | B32: 317 | C32: SECRETARIA DE COORDINACION | D32: 6178 | E32: MONROY ENRIQUEZ MARIEL NAYELY | F32: DEPARTAMENTO DE CONTROL DE CALIDAD | G32: MOEM901108MDFNNR06 | S32: M | T32: =IFERROR(VLOOKUP(O32, '[1]CURSOS 2025'!A:B, 2, FALSE), "") | U32: =SUM(' PLAN Y PROGRAMA ANUAL 2026'!$R32) -> 0
A33: {=IF(B33<>"",COUNTIF($B$19:B33,"<>"),"")} -> 9 | B33: 317 | C33: AUXILIAR ADMINISTRATIVO | D33: 6190 | E33: CORTES AGUILERA ARELI YAZMIN | F33: DEPARTAMENTO DE CONTROL DE CALIDAD | G33: COAA950711MDFRGR07 | S33: M | T33: =IFERROR(VLOOKUP(O33, '[1]CURSOS 2025'!A:B, 2, FALSE), "") | U33: =SUM(' PLAN Y PROGRAMA ANUAL 2026'!$R33:$R33) -> 0
A34: {=IF(B34<>"",COUNTIF($B$19:B34,"<>"),"")} -> 10 | B34: 317 | C34: TECNICO QUIMICO | D34: 206225 | E34: RAMÍREZ AMADOR RODOLFO ALBERTO | F34: DEPARTAMENTO DE CONTROL DE CALIDAD | G34: RAAR920117HDFMMD06 | K34: X | L34: X | M34: X | N34: EN LINEA | O34: CUMPLIMIENTO DEL REQUISITO CALIBRACIÓN DE INSTRUMENTOS DE MEDICIÓN | P34: 46073 | Q34: 46073 | R34: 2 | S34: H | T34: S/COSTO | U34: =SUM(R34:R34) -> 2
A35: {=IF(B35<>"",COUNTIF($B$19:B35,"<>"),"")} -> 11 | B35: 317 | C35: AYUDANTE DE LABORATORIO | D35: 3325 | E35: GUTIERREZ CRUZ JUAN CARLOS | F35: DEPARTAMENTO DE CONTROL DE CALIDAD | G35: GUCJ740518HDFTRN03 | K35: X | L35: X | M35: X | N35: EN LINEA | O35: EQUIPOS DE REFRIGERACIÓN Y AIRE ACONDICIONADO | P35: 46070 | Q35: 46070 | R35: 2 | S35: H | T35: S/COSTO | U35: =SUM(' PLAN Y PROGRAMA ANUAL 2026'!$R35:$R35) -> 2
A36: {=IF(B36<>"",COUNTIF($B$19:B36,"<>"),"")} -> 12 | B36: 317 | C36: AYUDANTE DE LABORATORIO | D36: 3282 | E36: GONZÁLEZ GLORIA MIGUEL | F36: DEPARTAMENTO DE CONTROL DE CALIDAD | G36: GOGM700207HGTNLG03 | S36: H | T36: =IFERROR(VLOOKUP(O36, '[1]CURSOS 2025'!A:B, 2, FALSE), "") | U36: =SUM(' PLAN Y PROGRAMA ANUAL 2026'!$R36) -> 0
A37: {=IF(B37<>"",COUNTIF($B$19:B37,"<>"),"")} -> 13 | B37: 317 | C37: AYUDANTE DE LABORATORIO | D37: 3726 | E37: MEJIA CASTILLO RAFAEL | F37: DEPARTAMENTO DE CONTROL DE CALIDAD | G37: MECR780129HMCJSF02 | S37: H | T37: =IFERROR(VLOOKUP(O37, '[1]CURSOS 2025'!A:B, 2, FALSE), "") | U37: =SUM(' PLAN Y PROGRAMA ANUAL 2026'!$R37) -> 0
A38: {=IF(B38<>"",COUNTIF($B$19:B38,"<>"),"")} -> 14 | B38: 317 | C38: AYUDANTE DE LABORATORIO | D38: 1780 | E38: CASTILLO GARCÍA JUAN CARLOS | F38: DEPARTAMENTO DE CONTROL DE CALIDAD | G38: CAGJ681219HDFSRN07 | S38: H | T38: =IFERROR(VLOOKUP(O38, '[1]CURSOS 2025'!A:B, 2, FALSE), "") | U38: =SUM(' PLAN Y PROGRAMA ANUAL 2026'!$R38) -> 0
A39: {=IF(B39<>"",COUNTIF($B$19:B39,"<>"),"")} -> 15 | B39: 317 | C39: TÉCNICO QUÍMICO | D39: 206278 | E39: ACOSTA AGUILLÓN RAFAEL | F39: DEPARTAMENTO DE CONTROL DE CALIDAD | G39: AOAR960904HDFCGF00 | K39: X | L39: X | M39: X | N39: EN LINEA | O39: CUMPLIMIENTO DEL REQUISITO CALIBRACIÓN DE INSTRUMENTOS DE MEDICIÓN | P39: 46073 | Q39: 46073 | R39: 2 | S39: H | T39: S/COSTO | U39: =SUM(' PLAN Y PROGRAMA ANUAL 2026'!$R39:$R39) -> 2
A40: {=IF(B40<>"",COUNTIF($B$19:B40,"<>"),"")} -> 16 | B40: 317 | C40: TÉCNICO QUÍMICO | D40: 206269 | E40: OLVERA LÓPEZ BLANCA EUGENIA | F40: DEPARTAMENTO DE CONTROL DE CALIDAD | G40: OELB980510MMCLPL02 | K40: X | L40: X | M40: X | N40: EN LINEA | O40: CUMPLIMIENTO DEL REQUISITO CALIBRACIÓN DE INSTRUMENTOS DE MEDICIÓN | P40: 46073 | Q40: 46073 | R40: 2 | S40: M | T40: S/COSTO | U40: =SUM(R40:R41) -> 4
K41: X | L41: X | M41: X | N41: EN LINEA | O41: ISO 9001 : 2026 Y SUS NUEVOS REQUERIMENTOS | P41: 46071 | Q41: 46071 | R41: 2 | S41: M | T41: S/COSTO
A42: {=IF(B42<>"",COUNTIF($B$19:B42,"<>"),"")} -> 17 | B42: 317 | C42: ANALISTA | D42: 62019 | E42: BERMUDEZ ROJAS CLARA ISABEL | F42: DEPARTAMENTO DE CONTROL DE CALIDAD | G42: BERC961024MBSRJL08 | K42: X | L42: X | M42: X | N42: EN LINEA | O42: ISO 9001 : 2026 Y SUS NUEVOS REQUERIMENTOS | P42: 46071 | Q42: 46071 | R42: 2 | S42: M | T42: S/COSTO | U42: =SUM(' PLAN Y PROGRAMA ANUAL 2026'!$R42:$R43) -> 4
A43: {=IF(B43<>"",COUNTIF($B$19:B43,"<>"),"")} | K43: X | L43: X | M43: X | N43: EN LINEA | O43: CUMPLIMIENTO DEL REQUISITO CALIBRACIÓN DE INSTRUMENTOS DE MEDICIÓN | P43: 46073 | Q43: 46073 | R43: 2 | S43: M | T43: S/COSTO
A44: {=IF(B44<>"",COUNTIF($B$19:B44,"<>"),"")} -> 18 | B44: 317 | C44: ANALISTA | D44: 62018 | E44: CRUZ MANRÍQUEZ JULIO MAXIMILIANO | F44: DEPARTAMENTO DE CONTROL DE CALIDAD | G44: CUMJ970109HBSRNL09 | K44: X | L44: X | M44: X | N44: EN LINEA | O44: ISO 9001 : 2026 Y SUS NUEVOS REQUERIMENTOS | P44: 46071 | Q44: 46071 | R44: 2 | S44: H | T44: S/COSTO | U44: =SUM(R44:R44) -> 2
A45: {=IF(B45<>"",COUNTIF($B$19:B45,"<>"),"")} -> 19 | B45: 317 | C45: TÉCNICO QUÍMICO | D45: 206264 | E45: ESPINOSA DÍAZ BRYAN EDWIN | F45: DEPARTAMENTO DE CONTROL DE CALIDAD | G45: EIDB940923HMCSZR00 | K45: X | L45: X | M45: X | N45: EN LINEA | O45: CUMPLIMIENTO DEL REQUISITO CALIBRACIÓN DE INSTRUMENTOS DE MEDICIÓN | P45: 46073 | Q45: 46073 | R45: 2 | S45: H | T45: S/COSTO | U45: =SUM(' PLAN Y PROGRAMA ANUAL 2026'!$R45:$R45) -> 2
A46: {=IF(B46<>"",COUNTIF($B$19:B46,"<>"),"")} -> 20 | B46: 317 | C46: TÉCNICO QUÍMICO | D46: 206295 | E46: MINGÜER URIBE ALDO ARIEL | F46: DEPARTAMENTO DE CONTROL DE CALIDAD | G46: MIUA950424HDFNRL04 | K46: X | L46: X | M46: X | N46: EN LINEA | O46: CUMPLIMIENTO DEL REQUISITO CALIBRACIÓN DE INSTRUMENTOS DE MEDICIÓN | P46: 46073 | Q46: 46073 | R46: 2 | S46: H | T46: S/COSTO | U46: =SUM(' PLAN Y PROGRAMA ANUAL 2026'!$R46:$R46) -> 2
A47: {=IF(B47<>"",COUNTIF($B$19:B47,"<>"),"")} -> 21 | B47: 317 | C47: TÉCNICO QUÍMICO | D47: 206298 | E47: GARCIA CHAVEZ DARIANA | F47: DEPARTAMENTO DE CONTROL DE CALIDAD | G47: GACD000131MDFRHRA6 | S47: M | T47: =IFERROR(VLOOKUP(O47, '[1]CURSOS 2025'!A:B, 2, FALSE), "") | U47: =SUM(R47:R47) -> 0
A48: {=IF(B48<>"",COUNTIF($B$19:B48,"<>"),"")} -> 22 | B48: 317 | C48: TÉCNICO QUÍMICO | D48: 206297 | E48: MILDRED BERENICE MOLINA LEONOR | F48: DEPARTAMENTO DE CONTROL DE CALIDAD | G48: MOLM000221MDFLNLA5 | S48: M | T48: =IFERROR(VLOOKUP(O48, '[1]CURSOS 2025'!A:B, 2, FALSE), "") | U48: =SUM(R48:R48) -> 0
A49: {=IF(B49<>"",COUNTIF($B$19:B49,"<>"),"")} -> 23 | B49: 317 | C49: AYUDANTE DE LABORATORIO | D49: 3952 | E49: MARTÍNEZ RITO CARLOS | F49: DEPARTAMENTO DE CONTROL DE CALIDAD | G49: MARC7901104HMCRTR06 | S49: H | U49: =SUM(R49) -> 0
A50: {=IF(B50<>"",COUNTIF($B$19:B50,"<>"),"")} -> 24 | B50: 317 | C50: TÉCNICO QUÍMICO | D50: 206309 | E50: NUÑEZ CISNEROS KEVIN ADAIR | F50: DEPARTAMENTO DE CONTROL DE CALIDAD | G50: NUCK000826HDFXSVA6 | S50: H | U50: =SUM(R50:R50) -> 0
A51: {=IF(B51<>"",COUNTIF($B$19:B51,"<>"),"")} -> 25 | B51: 317 | C51: TÉCNICO QUÍMICO | D51: 206310 | E51: INÉS GARCÍA MAYRA BERENICE | F51: DEPARTAMENTO DE CONTROL DE CALIDAD | G51: IEGM960919MMCNRY04 | S51: M | U51: =SUM(R51:R51) -> 0
A52: {=IF(B52<>"",COUNTIF($B$19:B52,"<>"),"")} -> 26 | B52: 317 | C52: TÉCNICO QUÍMICO | D52: 206317 | E52: RODRÍGUEZ LUNA ANDREA | F52: DEPARTAMENTO DE CONTROL DE CALIDAD | G52: ROLA000815MDFDNNA9 | S52: M | U52: =SUM(R52:R52) -> 0
A53: {=IF(B53<>"",COUNTIF($B$19:B53,"<>"),"")} -> 27 | B53: 317 | C53: QUÍMICO | D53: 206348 | E53: MENDEZ ESTRADA JOSE PABLO | F53: DEPARTAMENTO DE CONTROL DE CALIDAD | H53: X | I53: X | J53: X | N53: PRESENCIAL | O53: PLATICA DE INDUCCION AL PERSONAL DE NUEVO INGRESO | P53: 46149 | Q53: 46149 | R53: 1 | S53: H | T53: S/COSTO | U53: =SUM(R53:R54) -> 2
A54: {=IF(B54<>"",COUNTIF($B$19:B54,"<>"),"")} | H54: X | I54: X | J54: X | N54: PRESENCIAL | O54: PLATICA DE SEGURIDAD E HIGIENE AL PERSONAL DE NUEVO INGRESO | P54: 46149 | Q54: 46149 | R54: 1 | S54: H | T54: S/COSTO
A55: {=IF(B55<>"",COUNTIF($B$19:B55,"<>"),"")} -> 28 | B55: 317 | C55: CAPTURISTA | D55: 6325 | E55: SANCHEZ VILCHIS VANESSA | F55: DEPARTAMENTO DE CONTROL DE CALIDAD | S55: M | U55: =SUM(R55:R55) -> 0
A56: {=IF(B56<>"",COUNTIF($B$19:B56,"<>"),"")}
A57: {=IF(B57<>"",COUNTIF($B$19:B57,"<>"),"")} -> 29 | B57: 806 | C57: JEFE DE OFICINA DE PROGRAMACION | D57: 20520 | E57: PIZAÑA HERNÁNDEZ LAILA EDITH | F57: DEPARTAMENTO DE INFORMÁTICA | G57: PIHL630410MDFZRL00 | S57: M | T57: =IFERROR(VLOOKUP(O57, '[1]CURSOS 2025'!A:B, 2, FALSE), "") | U57: =SUM(' PLAN Y PROGRAMA ANUAL 2026'!$R57) -> 0
A58: {=IF(B58<>"",COUNTIF($B$19:B58,"<>"),"")} -> 30 | B58: 806 | C58: ANALISTA | D58: 206114 | E58: MUÑOZ GALLARDO ERIKA | F58: DEPARTAMENTO DE INFORMÁTICA | G58: MUGE821011MDFXLR07 | K58: X | L58: X | M58: X | N58: EN LINEA | O58: ACCIONES PARA ABORDAR RIESGOS Y OPORTUNIDADES | P58: 46069 | Q58: 46069 | R58: 2 | S58: M | T58: S/COSTO | U58: =SUM(R58:R60) -> 6
A59: {=IF(B59<>"",COUNTIF($B$19:B59,"<>"),"")} | K59: X | L59: X | M59: X | N59: EN LINEA | O59: ISO 9001 : 2026 Y SUS NUEVOS REQUERIMENTOS | P59: 46071 | Q59: 46071 | R59: 2 | S59: M | T59: S/COSTO
A60: {=IF(B60<>"",COUNTIF($B$19:B60,"<>"),"")} | K60: X | L60: X | M60: X | N60: EN LINEA | O60: CONTROL DE LA INFORMACIÓN DOCUMENTADA | P60: 46071 | Q60: 46071 | R60: 2 | S60: M | T60: S/COSTO
A61: {=IF(B61<>"",COUNTIF($B$19:B61,"<>"),"")} -> 31 | B61: 846 | C61: JEFE DE UNIDAD | D61: 5551 | E61: PIÑA RIVERA SONIA | F61: DEPARTAMENTO DE INFORMÁTICA | G61: PIRS761221MDFXVN00 | S61: M | U61: =SUM(R61:R61) -> 0
A62: {=IF(B62<>"",COUNTIF($B$19:B62,"<>"),"")} -> 32 | B62: 328 | C62: AUXILIAR ADMINISTRATIVO | D62: 5914 | E62: GUTIERREZ DE VELASCO SALCEDO ALAN | F62: DEPARTAMENTO DE INFORMÁTICA | G62: GUSA900101HDFTLL01 | S62: H | U62: =SUM(R62) -> 0
A63: {=IF(B63<>"",COUNTIF($B$19:B63,"<>"),"")} -> 33 | B63: 806 | C63: JEFE DE UNIDAD | D63: 205854 | E63: JIMÉNEZ ALEGRIA RICARDO | F63: DEPARTAMENTO DE INFORMÁTICA | G63: JIAR681110HDFMLC04 | S63: H | U63: =SUM(R63:R63) -> 0
A64: {=IF(B64<>"",COUNTIF($B$19:B64,"<>"),"")} -> 34 | B64: 806 | C64: JEFE DE UNIDAD | D64: 205879 | E64: SOLLANO CIFUENTES JUAN GUSTAVO | F64: DEPARTAMENTO DE INFORMÁTICA | G64: SOCJ770308HDFLFN01 | S64: H | U64: =SUM(R64:R64) -> 0
A65: {=IF(B65<>"",COUNTIF($B$19:B65,"<>"),"")} -> 35 | B65: 806 | C65: JEFE DE UNIDAD | D65: 5747 | E65: GUTIERREZ DE VELASCO SALCEDO ALAN | F65: DEPARTAMENTO DE INFORMÁTICA | G65: SATE800105HDFNRD07 | S65: H | T65: =IFERROR(VLOOKUP(O65, '[1]CURSOS 2025'!A:B, 2, FALSE), "") | U65: =SUM(R65:R65) -> 0
A66: {=IF(B66<>"",COUNTIF($B$19:B66,"<>"),"")} -> 36 | B66: 806 | C66: AUXILIAR ADMINISTRATIVO | D66: 5888 | E66: ALCANTARA GARCÍA LUZ MARIA GUADALUPE | F66: DEPARTAMENTO DE INFORMÁTICA | G66: AAGL740909MDFLRZ07 | S66: M | U66: =SUM(R66) -> 0
A67: {=IF(B67<>"",COUNTIF($B$19:B67,"<>"),"")} -> 37 | B67: 806 | C67: JEFE DE UNIDAD | D67: 5747 | E67: SÀNCHEZ TORRES EDGAR RICARDO | F67: DEPARTAMENTO DE INFORMÁTICA | G67: SATE800105HDFNRD07 | S67: H | U67: =SUM(R67) -> 0
A68: {=IF(B68<>"",COUNTIF($B$19:B68,"<>"),"")}
A69: {=IF(B69<>"",COUNTIF($B$19:B69,"<>"),"")} -> 38 | B69: 226 | C69: SUBGERENTE DE ABASTO | D69: 80183 | E69: AQUINO QUINTANA JUAN ALBERTO | F69: SUBGERENCIA DE ABASTO | G69: AUQJ660502HDFQNN08 | K69: X | L69: X | M69: X | N69: EN LINEA | O69: ISO 9001 : 2026 Y SUS NUEVOS REQUERIMENTOS | P69: 46071 | Q69: 46071 | R69: 2 | S69: H | T69: S/COSTO | U69: =SUM(R69:R70) -> 42
K70: X | L70: X | M70: X | N70: EN LINEA | O70: ATENCIÓN SOCIOSANITARIA DE LAS PERSONAS MAYORES EN EL DOMICILIO. (FORTALECIMIENTO DE LAS COMPETENCIAS EN EL PERSONAL DE ENFERMERIA) | P70: 46111 | Q70: 46111 | R70: 40 | S70: H | T70: S/COSTO
A71: {=IF(B71<>"",COUNTIF($B$19:B71,"<>"),"")} -> 39 | B71: 226 | C71: JEFE DE OFICINA | D71: 205309 | E71: RUIZ ARROYO AMPARO | F71: SUBGERENCIA DE ABASTO | G71: RUAA670720MDFZRM02 | S71: M | U71: =SUM(R71:R71) -> 0
A72: {=IF(B72<>"",COUNTIF($B$19:B72,"<>"),"")}
A73: {=IF(B73<>"",COUNTIF($B$19:B73,"<>"),"")} -> 40 | B73: 234 | C73: SUPERVISOR | D73: 1253 | E73: HERRERA VELAZQUEZ VICENTE | F73: TALLER AUTOMOTRIZ | G73: HEVV650405HMCRLC04 | S73: H | U73: =SUM(R73:R73) -> 0
A74: {=IF(B74<>"",COUNTIF($B$19:B74,"<>"),"")} -> 41 | B74: 234 | C74: AUXILIAR ADMINISTRATIVO | D74: 5884 | E74: RENTERIA CASTILLO EDITH | F74: TALLER AUTOMOTRIZ | G74: RECE820310MMCNSD03 | S74: M | U74: =SUM(R74:R74) -> 0
A75: {=IF(B75<>"",COUNTIF($B$19:B75,"<>"),"")} -> 42 | B75: 234 | C75: PINTOR AUTOMOTRIZ | D75: 3341 | E75: URBINA AGUILAR OSCAR | F75: TALLER AUTOMOTRIZ | G75: UIAO671230HDFRGS04 | S75: H | U75: =SUM(R75) -> 0
A76: {=IF(B76<>"",COUNTIF($B$19:B76,"<>"),"")} -> 43 | B76: 234 | C76: MECÁNICO GASOLINA | D76: 3482 | E76: MONROY GARCÍA EFREN | F76: TALLER AUTOMOTRIZ | G76: MOGE780618HDFNRF12 | S76: H | U76: =SUM(R76:R76) -> 0
A77: {=IF(B77<>"",COUNTIF($B$19:B77,"<>"),"")} -> 44 | B77: 234 | C77: MECANICO "A" | D77: 3513 | E77: ARANDA GUTIERREZ GABRIEL | F77: TALLER AUTOMOTRIZ | G77: AAGG600227HDFRTB13 | S77: H | U77: =SUM(R77) -> 0
A78: {=IF(B78<>"",COUNTIF($B$19:B78,"<>"),"")} -> 45 | B78: 234 | C78: MECÁNICO GASOLINA | D78: 3137 | E78: SÁNCHEZ OCHOA ABEL | F78: TALLER AUTOMOTRIZ | G78: SAOA690426HMCNCB01 | S78: H | U78: =SUM(R78) -> 0
A79: {=IF(B79<>"",COUNTIF($B$19:B79,"<>"),"")} -> 46 | B79: 234 | C79: MECÁNICO GASOLINA | D79: 3142 | E79: ZAMORANO MORALES CESAR | F79: TALLER AUTOMOTRIZ | G79: ZAMC780814HDFMRS08 | S79: H | U79: =SUM(R79:R79) -> 0
A80: {=IF(B80<>"",COUNTIF($B$19:B80,"<>"),"")} -> 47 | B80: 234 | C80: MECÁNICO DIESEL | D80: 3135 | E80: CAMPOS ORTIZ IVAN | F80: TALLER AUTOMOTRIZ | G80: CAOI760627HMCMRV09 | S80: H | T80: =IFERROR(VLOOKUP(O80, '[1]CURSOS 2025'!A:B, 2, FALSE), "") | U80: =SUM(R80:R80) -> 0
A81: {=IF(B81<>"",COUNTIF($B$19:B81,"<>"),"")} -> 48 | B81: 234 | C81: HOJALATERO | D81: 3704 | E81: MENDEZ BRITO JOSÉ ALBERTO | F81: TALLER AUTOMOTRIZ | G81: MEBA690408HDFNRL06 | S81: H | T81: =IFERROR(VLOOKUP(O81, '[1]CURSOS 2025'!A:B, 2, FALSE), "") | U81: =SUM(R81:R81) -> 0
A82: {=IF(B82<>"",COUNTIF($B$19:B82,"<>"),"")} -> 49 | B82: 234 | C82: MECÁNICO GASOLINA | D82: 3158 | E82: HERNÁNDEZ LÓPEZ FRANCISCO JAVIER | F82: TALLER AUTOMOTRIZ | G82: HELF780608HDFRPR00 | S82: H | T82: =IFERROR(VLOOKUP(O82, '[1]CURSOS 2025'!A:B, 2, FALSE), "") | U82: =SUM(R82:R82) -> 0
A83: {=IF(B83<>"",COUNTIF($B$19:B83,"<>"),"")} -> 50 | B83: 234 | C83: SOLDADOR AUTOMOTRIZ | D83: 3087 | E83: SANTIAGO ZARATE LUIS ENRIQUE | F83: TALLER AUTOMOTRIZ | G83: SAZL650620HDFNRS01 | S83: H | T83: =IFERROR(VLOOKUP(O83, '[1]CURSOS 2025'!A:B, 2, FALSE), "") | U83: =SUM(R83:R83) -> 0
A84: {=IF(B84<>"",COUNTIF($B$19:B84,"<>"),"")} -> 51 | B84: 234 | C84: JEFE DE UNIDAD | D84: 206273 | E84: RAMÍREZ CORTAZAR JULIO CESAR | F84: TALLER AUTOMOTRIZ | G84: RACJ730324HDFMRL01 | S84: H | T84: =IFERROR(VLOOKUP(O84, '[1]CURSOS 2025'!A:B, 2, FALSE), "") | U84: =SUM(R84:R84) -> 0
A85: {=IF(B85<>"",COUNTIF($B$19:B85,"<>"),"")}
A86: {=IF(B86<>"",COUNTIF($B$19:B86,"<>"),"")} -> 52 | B86: 615 | C86: COORDINADOR GENERAL | D86: 206245 | E86: JÍMENEZ BARRERA ANGÉLICA MARÍA | F86: ATENCIÓN Y SERVICIOS A CONCESIONARIOS | G86: JIBA660815MDFMRN03 | K86: X | L86: X | M86: X | N86: EN LINEA | O86: ISO 9001 : 2026 Y SUS NUEVOS REQUERIMENTOS | P86: 46071 | Q86: 46071 | R86: 2 | S86: M | T86: S/COSTO | U86: =SUM(R86) -> 2
A87: {=IF(B87<>"",COUNTIF($B$19:B87,"<>"),"")} -> 53 | B87: 615 | C87: JEFE DE UNIDAD | D87: 206214 | E87: VARGAS GOMEZ KARLA | F87: ATENCIÓN Y SERVICIOS A CONCESIONARIOS | G87: VAGK780609MDFRMR00 | S87: M | T87: =IFERROR(VLOOKUP(O87, '[1]CURSOS 2025'!A:B, 2, FALSE), "") | U87: =SUM(R87:R87) -> 0
A88: {=IF(B88<>"",COUNTIF($B$19:B88,"<>"),"")}
A89: {=IF(B89<>"",COUNTIF($B$19:B89,"<>"),"")} -> 54 | B89: 325 | C89: JEFE DE OFICINA | D89: 206086 | E89: SÁNCHEZ LANDEROS ESMERALDA | F89: SUBGERENCIA DE OPERACIONES | G89: SALE781017MDFNNS04 | K89: X | L89: X | M89: X | N89: EN LINEA | O89: ACCIONES PARA ABORDAR RIESGOS Y OPORTUNIDADES | P89: 46069 | Q89: 46069 | R89: 2 | S89: M | T89: S/COSTO | U89: =SUM(R89:R91) -> 6
A90: {=IF(B90<>"",COUNTIF($B$19:B90,"<>"),"")} | K90: X | L90: X | M90: X | N90: EN LINEA | O90: ISO 9001 : 2026 Y SUS NUEVOS REQUERIMENTOS | P90: 46071 | Q90: 46071 | R90: 2 | S90: M | T90: S/COSTO
A91: {=IF(B91<>"",COUNTIF($B$19:B91,"<>"),"")} | K91: X | L91: X | M91: X | N91: EN LINEA | O91: CONTROL DE LA INFORMACIÓN DOCUMENTADA | P91: 46071 | Q91: 46071 | R91: 2 | S91: M | T91: S/COSTO
A92: {=IF(B92<>"",COUNTIF($B$19:B92,"<>"),"")} -> 55 | B92: 325 | C92: JEFE DE UNIDAD | D92: 602 | E92: CARDENAS PONCE MARIA GUADALUPE | F92: SUBGERENCIA DE OPERACIONES | G92: CAPG640227MDFRND09 | S92: M | T92: =IFERROR(VLOOKUP(O92, '[1]CURSOS 2025'!A:B, 2, FALSE), "") | U92: =SUM(R92) -> 0
A93: {=IF(B93<>"",COUNTIF($B$19:B93,"<>"),"")}
A94: {=IF(B94<>"",COUNTIF($B$19:B94,"<>"),"")} -> 56 | B94: 615 | C94: SUPERVISOR | D94: 205895 | E94: GARCÍA MARTÍNEZ HILDA | F94: ATENCIÓN Y SERVICIOS A CONCESIONARIOS | G94: GAMH740417MDFRRL06 | S94: M | T94: =IFERROR(VLOOKUP(O94, '[1]CURSOS 2025'!A:B, 2, FALSE), "") | U94: =SUM(R94) -> 0
A95: {=IF(B95<>"",COUNTIF($B$19:B95,"<>"),"")} -> 57 | B95: 615 | C95: JEFE DE UNIDAD | D95: 205502 | E95: SÁNCHEZ MALDONADO FRANCISCO | F95: ATENCIÓN Y SERVICIOS A CONCESIONARIOS | G95: SAMF721006HDFNLR01 | S95: H | T95: =IFERROR(VLOOKUP(O95, '[1]CURSOS 2025'!A:B, 2, FALSE), "") | U95: =SUM(R95) -> 0
A96: {=IF(B96<>"",COUNTIF($B$19:B96,"<>"),"")} -> 58 | B96: 615 | C96: JEFE DE UNIDAD DE OPERACIÓN | D96: 20871 | E96: AVIÑA ZAMORANO SAUL | F96: ATENCIÓN Y SERVICIOS A CONCESIONARIOS | G96: AIZS710412HDFVML02 | S96: H | T96: =IFERROR(VLOOKUP(O96, '[1]CURSOS 2025'!A:B, 2, FALSE), "") | U96: =SUM(R96) -> 0
A97: {=IF(B97<>"",COUNTIF($B$19:B97,"<>"),"")} -> 59 | B97: 615 | C97: AUXILIAR ADMINISTRATIVO | D97: 5811 | E97: ARENAS CARMONA HATSUE SAYURI | F97: ATENCIÓN Y SERVICIOS A CONCESIONARIOS | G97: AECH840215MMCRRT00 | S97: M | T97: =IFERROR(VLOOKUP(O97, '[1]CURSOS 2025'!A:B, 2, FALSE), "") | U97: =SUM(R97:R97) -> 0
A98: {=IF(B98<>"",COUNTIF($B$19:B98,"<>"),"")} -> 60 | B98: 615 | C98: AUXILIAR ADMINISTRATIVO | D98: 5875 | E98: ZETINA ALFARO CESAR AUGUSTO | F98: ATENCIÓN Y SERVICIOS A CONCESIONARIOS | G98: ZEAC770816HDFTLS05 | S98: H | T98: =IFERROR(VLOOKUP(O98, '[1]CURSOS 2025'!A:B, 2, FALSE), "") | U98: =SUM(R98:R98) -> 0
A99: {=IF(B99<>"",COUNTIF($B$19:B99,"<>"),"")} -> 61 | B99: 615 | C99: AUXILIAR ADMINISTRATIVO | D99: 5788 | E99: CONTRERAS JASSO MARIA TRINIDAD | F99: ATENCIÓN Y SERVICIOS A CONCESIONARIOS | G99: COJT761225MMCNSR03 | S99: M | T99: =IFERROR(VLOOKUP(O99, '[1]CURSOS 2025'!A:B, 2, FALSE), "") | U99: =SUM(R99) -> 0
A100: {=IF(B100<>"",COUNTIF($B$19:B100,"<>"),"")} -> 62 | B100: 615 | C100: APOYO TECNICO A CONCESIONES | D100: 205974 | E100: GUZMÁN FUENTES CARLOS JONATHAN | F100: ATENCIÓN Y SERVICIOS A CONCESIONARIOS | G100: GUFC860425HDFZNR03 | S100: H | T100: =IFERROR(VLOOKUP(O100, '[1]CURSOS 2025'!A:B, 2, FALSE), "") | U100: =SUM(R100) -> 0
A101: {=IF(B101<>"",COUNTIF($B$19:B101,"<>"),"")} -> 63 | B101: 615 | C101: APOYO TECNICO A CONCESIONES | D101: 205948 | E101: RAMÍREZ NUÑEZ BELGICA | F101: ATENCIÓN Y SERVICIOS A CONCESIONARIOS | G101: RANB720208MDFMXL09 | S101: M | T101: =IFERROR(VLOOKUP(O101, '[1]CURSOS 2025'!A:B, 2, FALSE), "") | U101: =SUM(R101) -> 0
A102: {=IF(B102<>"",COUNTIF($B$19:B102,"<>"),"")} -> 64 | B102: 615 | C102: APOYO TECNICO A CONCESIONES | D102: 205816 | E102: ORTEGA MARTÍNEZ QUINTINA | F102: ATENCIÓN Y SERVICIOS A CONCESIONARIOS | G102: OEMQ651031MOCRRN01 | S102: H | T102: =IFERROR(VLOOKUP(O102, '[1]CURSOS 2025'!A:B, 2, FALSE), "") | U102: =SUM(R102) -> 0
A103: {=IF(B103<>"",COUNTIF($B$19:B103,"<>"),"")} -> 65 | B103: 615 | C103: APOYO TECNICO A CONCESIONES | D103: 205768 | E103: CRUZ ROJAS GASPAR | F103: ATENCIÓN Y SERVICIOS A CONCESIONARIOS | G103: CURG670106HDFRJS09 | S103: H | T103: =IFERROR(VLOOKUP(O103, '[1]CURSOS 2025'!A:B, 2, FALSE), "") | U103: =SUM(R103) -> 0
A104: {=IF(B104<>"",COUNTIF($B$19:B104,"<>"),"")} -> 66 | B104: 615 | C104: APOYO TECNICO A CONCESIONES | D104: 205753 | E104: UREÑA RUIZ PATRICIA | F104: ATENCIÓN Y SERVICIOS A CONCESIONARIOS | G104: UERP700314MMCRZT03 | S104: M | T104: =IFERROR(VLOOKUP(O104, '[1]CURSOS 2025'!A:B, 2, FALSE), "") | U104: =SUM(R104) -> 0
A105: {=IF(B105<>"",COUNTIF($B$19:B105,"<>"),"")} -> 67 | B105: 615 | C105: JEFE DE UNIDAD | D105: 207683 | E105: BARRIGA VELEZ BARBARA CELIA | F105: ATENCIÓN Y SERVICIOS A CONCESIONARIOS | G105: BAVB790609MMCRLR03 | S105: M | T105: =IFERROR(VLOOKUP(O105, '[1]CURSOS 2025'!A:B, 2, FALSE), "") | U105: =SUM(R105) -> 0
A106: {=IF(B106<>"",COUNTIF($B$19:B106,"<>"),"")} -> 68 | B106: 615 | C106: JEFE DE UNIDAD | D106: 206781 | E106: MORENO CORTES DANIEL | F106: ATENCIÓN Y SERVICIOS A CONCESIONARIOS | G106: MOCD670502HDFRRN06 | S106: H | T106: =IFERROR(VLOOKUP(O106, '[1]CURSOS 2025'!A:B, 2, FALSE), "") | U106: =SUM(R106) -> 0
A107: {=IF(B107<>"",COUNTIF($B$19:B107,"<>"),"")} -> 69 | B107: 615 | C107: AUXILIAR ADMINISTRATIVO | D107: 62025 | E107: MIRANDA ALCANTARA DANIELA KARINA | F107: ATENCIÓN Y SERVICIOS A CONCESIONARIOS | G107: MIAD010628MDFRLNA2 | K107: X | L107: X | M107: X | N107: EN LINEA | O107: TRABAJO EN EQUIPO | P107: 46132 | Q107: 46132 | R107: 20 | S107: M | T107: =IFERROR(VLOOKUP(O107, '[1]CURSOS 2025'!A:B, 2, FALSE), "") -> S/COSTO | U107: =SUM(R107:R108) -> 40
K108: X | L108: X | M108: X | N108: EN LINEA | O108: LENGUAJE CIUDADANO | P108: 46133 | Q108: 46133 | R108: 20 | S108: M | T108: S/COSTO
A109: {=IF(B109<>"",COUNTIF($B$19:B109,"<>"),"")} -> 70 | B109: 615 | C109: ANALISTA | D109: 206315 | E109: RAMÍREZ MEDINA ANA ISABEL | F109: ATENCIÓN Y SERVICIOS A CONCESIONARIOS | S109: M | T109: =IFERROR(VLOOKUP(O109, '[1]CURSOS 2025'!A:B, 2, FALSE), "") | U109: =SUM(R109:R109) -> 0
...

Sheet CURSOS 2026
A2: Cursos | B2: $ | C2: MODALIDAD | D2: DURACIÓN
A3: ATENCIÓN SOCIOSANITARIA DE LAS PERSONAS MAYORES EN EL DOMICILIO. (FORTALECIMIENTO DE LAS COMPETENCIAS EN EL PERSONAL DE ENFERMERIA) | B3: S/COSTO | C3: EN LINEA | D3: 40
A4: OPERACIÓN DE MONTACARGAS | B4: S/COSTO | C4: EN LINEA | D4: 2
A5: CURSO PARA LA OPERACIÓN DEL MÓDULO DE PROCEDIMIENTOS DE CONTRATACIÓN EN LA PLATAFORMA COMPRAS MX | B5: S/COSTO | C5: EN LINEA | D5: 30
A6: REGULARIZACIÓN NORMATIVA EN MATERIA DE IMPACTO AMBIENTAL | B6: S/COSTO | C6: EN LINEA | D6: 2
A7: FÚTBOL SIN CORRER: FUNDAMENTOS PARA UN JUEGOLIMPIO Y SEGURO | B7: S/COSTO | C7: EN LINEA | D7: 2
A8: ABORDAJE DE TRASTORNOS POR CONSUMO DE SUSTANCIAS EN EL TERCER NIVEL DE ATENCIÓN CON BASE EN EL NUEVO MODELO MEXICANO | B8: S/COSTO | C8: EN LINEA | D8: 40
A9: DIVERSIDAD SEXUAL Y DERECHOS HUMANOS | B9: S/COSTO | C9: EN LINEA | D9: 30
A10: ACCIONES PARA ABORDAR RIESGOS Y OPORTUNIDADES | B10: S/COSTO | C10: EN LINEA | D10: 2
A11: EQUIPOS DE REFRIGERACIÓN Y AIRE ACONDICIONADO | B11: S/COSTO | C11: EN LINEA | D11: 2
A12: ISO 9001 : 2026 Y SUS NUEVOS REQUERIMENTOS | B12: S/COSTO | C12: EN LINEA | D12: 2
A13: CONTROL DE LA INFORMACIÓN DOCUMENTADA | B13: S/COSTO | C13: EN LINEA | D13: 2
A14: CUMPLIMIENTO DEL REQUISITO CALIBRACIÓN DE INSTRUMENTOS DE MEDICIÓN | B14: S/COSTO | C14: EN LINEA | D14: 2
... A38: PERSONAS CON DISCAPACIDAD;TRANSFORMANDO BARRERAS EN OPORTUNIDADES | B38: S/COSTO | C38: EN LINEA | D38: 30

Sheet CURSOS 2025
A1: 1 | B1: 2 | C1: 3 | D1: 4 | E1: 5
A2: Cursos | B2: $ | C2: MODALIDAD | D2: DURACIÓN
A3: ABORDAJE DE TRASTORNO POR CONSUMO DE SUSTANCIAS EN EL TERCER NIVEL DE ATENCIÓN CON BASE EN EL NUEVO MODELO MEXICANO | B3: S/COSTO | C3: EN LÍNEA | D3: 40
A4: ATENCIÓN A TRANSTORNOS MENTALES BASADA EN LA ESTRATEGIA mhGAP | B4: S/COSTO | C4: EN LÍNEA | D4: 40
A5: ESGUINCE DE TOBILLO Y MUÑECA | B5: S/COSTO | C5: EN LÍNEA | D5: 5
A6: ABC DE LA OBESIDAD | B6: S/COSTO | C6: EN LÍNEA | D6: 10
A7: PREVENCIÓN DE LA TRATA DE PERSONAS | B7: S/COSTO | C7: EN LÍNEA | D7: 40
A8: DERECHOS HUMANOS Y SALUD | B8: S/COSTO | C8: EN LÍNEA | D8: 40
A9: MARKETING DIGITAL I | B9: S/COSTO | C9: EN LÍNEA | D9: 40
A10: PLÁTICA DE INDUCCIÓN AL PERSONAL DE NUEVO INGRESO | B10: S/COSTO | C10: PRESENCIAL | D10: 1
A11: PLÁTICA DE SEGURIDAD E HIGIENE INDUSTRIAL AL PERSONAL DE NUEVO INGRESO | B11: S/COSTO | C11: PRESENCIAL | D11: 1
A12: EXCEL INTERMEDIO | B12: S/COSTO | C12: EN LÍNEA | D12: 2
A13: PLATICA DE INDUCCIÓN IMSS | B13: S/COSTO | C13: PRESENCIAL | D13: 1
A14: APLICACIONES DE LA INTELIGENCIA ARTIFICIAL EN EL USO Y OPTIMIZACIÓN DE SISTMAS DE ENERGÍA RENOVABLE | B14: S/COSTO | C14: PRESENCIAL | D14: 2
... A133: REDESCUBRIENDO AL IMSS | B133: S/COSTO | C133: EN LÍNEA | D133: 5
B134: S/COSTO
B135: S/COSTO
B136: S/COSTO
B137: S/COSTO
B138: S/COSTO
B139: S/COSTO
B140: S/COSTO
B141: S/COSTO
B142: S/COSTO
B143: S/COSTO
B144: S/COSTO
B145: S/COSTO
... B159: S/COSTO

Sheet Activos 2023
B2: PUESTO | C2: NÓMINA | D2: NOMBRE | E2: ÁREA | F2: CURP
B3: MÉDICO | C3: 206263 | D3: GUADARRAMA FERNANDEZ DE LARA SALVADOR | E3: RELACIONES INDUSTRIALES
B4: ANALISTA DE PROYECTO F | C4: 62018 | D4: CRUZ MANRIQUEZ JULIO MAXIMILIANO | E4: CONTROL DE CALIDAD
B5: ANALISTA DE PROYECTO F | C5: 62019 | D5: ROJAS BERMUDEZ CLARA ISABEL | E5: CONTROL DE CALIDAD
B6: AYUDANTE GENERAL | C6: 3961 | D6: MALDONADO OLVERA ELADIO | E6: PRODUCCIÓN
B7: AYUDANTE GENERAL | C7: 3962 | D7: PÉREZ CORONA JESÚS MANUEL | E7: PRODUCCIÓN
B8: AYUDANTE GENERAL | C8: 3963 | D8: SAUCEDO VILLALON JUAN JOSÉ | E8: PRODUCCIÓN
B9: AYUDANTE GENERAL | C9: 3966 | D9: RAMÍREZ CONTRERAS JULIO CESAR | E9: PRODUCCIÓN
B10: AYUDANTE GENERAL | C10: 3971 | D10: POBLANO ROSAS DIEGO ANTONIO | E10: PRODUCCIÓN
B11: AYUDANTE GENERAL | C11: 3973 | D11: HERRIANDE ALDANA MAXIMINA | E11: PRODUCCIÓN
B12: AYUDANTE GENERAL | C12: 3974 | D12: AGUILAR MORALES JOSÉ IVAN | E12: PRODUCCIÓN
B13: AYUDANTE GENERAL | C13: 3975 | D13: GONZÁLEZ VILCHIS JAIR | E13: PRODUCCIÓN
B14: AYUDANTE GENERAL | C14: 3976 | D14: RIOS GALINDO MARCOS | E14: PRODUCCIÓN
... B40: JEFE DE UNIDAD | C40: 206273 | D40: RAMIREZ CORTAZAR JULIO CESAR | E40: TALLER AUTOMOTRIZ

Sheet Cursos 2023
A1: Cursos
A2: ¿COMÓ ENTENDER EL PRESUPUESTO? EL GASTO PÚBLICO A TRAVÉS DE LOS DATOS | B2: S/COSTO | C2: EN LÍNEA | D2: 60 hrs
A3: ¿POR QUÉ AMAMOS DEMASIADO? PERO DEMASIADO MAL | B3: S/COSTO | C3: EN LÍNEA | D3: 2 hrs
A4: 5 "S" | B4: S/COSTO | C4: EN LÍNEA | D4: 3 hrs
A5: ABC DE LA OBESIDAD | B5: S/COSTO | C5: EN LÍNEA | D5: 10 hrs
A6: ACTIVACIÓN FÍSICA PARA EL PERSONAL QUE INTEGRA LA BRIGADA CONTRA INCENDIOS | B6: S/COSTO | C6: PRESENCIAL | D6: 1 hrs
A7: ACTIVACIÓN/PLÁTICA FÍSICA PARA EL PERSONAL QUE INTEGRA LA BRIGADA CONTRA INCENDIOS | B7: S/COSTO | C7: PRESENCIAL | D7: 1 hrs
A8: ACTIVIDAD FÍSICA: RETORNO SEGURO | B8: S/COSTO | C8: EN LÍNEA | D8: 3 hrs
A9: ACTIVIDADES CULTURALES: RETORNO SEGURO | B9: S/COSTO | C9: EN LÍNEA | D9: 5 hrs
A10: ADICCIONES Y SUS REPERCUCIONES EN EL ENTORNO LABORAL (TRABAJADORES) | B10: S/COSTO | C10: EN LÍNEA | D10: 10 hrs
A11: ADMINISTRACIÓN DE LOS ARCHIVOS DOCUMENTALES DE LICONSA | B11: S/COSTO | C11: EN LÍNEA | D11: 2 hrs
A12: ADMINISTRACIÓN PÚBLICA FEDERAL LIBRE DE VIOLENCIA. COMBATE AL ACOSO SEXUAL Y HOSTIGAMIENTO SEXUAL | B12: S/COSTO | C12: EN LÍNEA | D12: 8 hrs
A13: ALIMENTACIÓN, CLAVE PARA EL CONTROL DE LA DIABETES | B13: S/COSTO | C13: EN LÍNEA | D13: 20 hrs
... A186: YO DECIDO: MI SEXUALIDAD, MIS DECISIONES RESPONSABLES | B186: S/COSTO | C186: EN LÍNEA | D186: 2 hrs

Sheet BAJA 2024 (TRABAJADORES)
A1: 301 | B1: GERENTE | C1: 80181 | D1: DOMÍNGUEZ SANCHEZ JESÚS | E1: GERENCIA | F1: DOSJ520304HTSMNS08 | M1: =IF(N1="","",VLOOKUP(N1,'CURSOS 2025'!$A$3:$D$199,3,FALSE)) | Q1: =IF(N1="","",VLOOKUP(N1,'CURSOS 2025'!$A$3:$D$199,4,FALSE)) | R1: M | S1: =IF(N1="","",VLOOKUP(N1,'CURSOS 2025'!$A$3:$B$199,2,FALSE))
A2: 301 | B2: JEFE DE UNIDAD | C2: 206275 | D2: MAGAÑA MADIEDO EMMANUEL | E2: GERENCIA | F2: MAME990722HMCGDM06 | M2: =IF(N2="","",VLOOKUP(N2,'CURSOS 2025'!$A$3:$D$199,3,FALSE)) | Q2: =IF(N2="","",VLOOKUP(N2,'CURSOS 2025'!$A$3:$D$199,4,FALSE)) | R2: M | S2: =IF(N2="","",VLOOKUP(N2,'CURSOS 2025'!$A$3:$B$199,2,FALSE))
A3: 301 | B3: COORDINADOR GENERAL | C3: 206227 | D3: RAMOS OLIVARES MARIA DEL SOCORRO | E3: GERENCIA | F3: RAOS620418MHGMLC04 | M3: =IF(N3="","",VLOOKUP(N3,'CURSOS 2025'!$A$3:$D$199,3,FALSE)) | Q3: =IF(N3="","",VLOOKUP(N3,'CURSOS 2025'!$A$3:$D$199,4,FALSE)) | R3: F | S3: =IF(N3="","",VLOOKUP(N3,'CURSOS 2025'!$A$3:$B$199,2,FALSE))
A4: 301 | B4: JEFE DE UNIDAD | C4: 206228 | D4: PADILLA CONTRERAS JENNIFER | E4: GERENCIA | F4: PACJ910310MMCDNN05 | M4: =IF(N4="","",VLOOKUP(N4,'CURSOS 2025'!$A$3:$D$199,3,FALSE)) | Q4: =IF(N4="","",VLOOKUP(N4,'CURSOS 2025'!$A$3:$D$199,4,FALSE)) | R4: F | S4: =IF(N4="","",VLOOKUP(N4,'CURSOS 2025'!$A$3:$B$199,2,FALSE))
A5: 301 | B5: AUXILIAR PROYECTO E | C5: 62016 | D5: LOPEZ PADILLA ILSE JOCELYN | E5: GERENCIA | F5: LOPI960114MDFPDL08 | M5: =IF(N5="","",VLOOKUP(N5,'CURSOS 2025'!$A$3:$D$199,3,FALSE)) | Q5: =IF(N5="","",VLOOKUP(N5,'CURSOS 2025'!$A$3:$D$199,4,FALSE)) | R5: F | S5: =IF(N5="","",VLOOKUP(N5,'CURSOS 2025'!$A$3:$B$199,2,FALSE))
A6: 317 | B6: QUIMICO | C6: 20502 | D6: RIVERA ORDOÑEZ JOSÉ ROBERTO | E6: CONTROL DE CALIDAD | F6: RIOR611005HGRVRB05 | M6: =IF(N6="","",VLOOKUP(N6,'CURSOS 2025'!$A$3:$D$199,3,FALSE)) | Q6: =IF(N6="","",VLOOKUP(N6,'CURSOS 2025'!$A$3:$D$199,4,FALSE)) | R6: M | S6: =IF(N6="","",VLOOKUP(N6,'CURSOS 2025'!$A$3:$B$199,2,FALSE))
A7: 317 | B7: ANALISTA DE PROYECTO F | C7: 62018 | D7: CRUZ MANRIQUEZ JULIO MAXIMILIANO | E7: CONTROL DE CALIDAD | F7: CUMJ970109HBSRNL09 | M7: =IF(N7="","",VLOOKUP(N7,'CURSOS 2025'!$A$3:$D$199,3,FALSE)) | Q7: =IF(N7="","",VLOOKUP(N7,'CURSOS 2025'!$A$3:$D$199,4,FALSE)) | R7: M | S7: =IF(N7="","",VLOOKUP(N7,'CURSOS 2025'!$A$3:$B$199,2,FALSE))
A8: 317 | B8: ANALISTA DE PROYECTO F | C8: 62019 | D8: ROJAS BERMUDEZ CLARA ISABEL | E8: CONTROL DE CALIDAD | F8: BERC961024MBSRJL08 | M8: =IF(N8="","",VLOOKUP(N8,'CURSOS 2025'!$A$3:$D$199,3,FALSE)) | Q8: =IF(N8="","",VLOOKUP(N8,'CURSOS 2025'!$A$3:$D$199,4,FALSE)) | R8: F | S8: =IF(N8="","",VLOOKUP(N8,'CURSOS 2025'!$A$3:$B$199,2,FALSE))
A9: 317 | B9: OPERADOR DE SERVICIOS B | C9: 62024 | D9: SUÁREZ SUÁREZ ANGELES ELIZABETH | E9: CONTROL DE CALIDAD | F9: SUSA960917MVZRRN04 | M9: =IF(N9="","",VLOOKUP(N9,'CURSOS 2025'!$A$3:$D$199,3,FALSE)) | Q9: =IF(N9="","",VLOOKUP(N9,'CURSOS 2025'!$A$3:$D$199,4,FALSE)) | R9: F | S9: =IF(N9="","",VLOOKUP(N9,'CURSOS 2025'!$A$3:$B$199,2,FALSE))
A10: 234 | B10: JEFE DE UNIDAD | C10: 206250 | D10: ALVAREZ TOSTADO HERNÁNDEZ JESSICA MICHEL | E10: TALLER AUTOMOTRIZ | F10: AAHJ960519MDFLRS02 | M10: =IF(N10="","",VLOOKUP(N10,'CURSOS 2025'!$A$3:$D$199,3,FALSE)) | Q10: =IF(N10="","",VLOOKUP(N10,'CURSOS 2025'!$A$3:$D$199,4,FALSE)) | R10: F | S10: =IF(N10="","",VLOOKUP(N10,'CURSOS 2025'!$A$3:$B$199,2,FALSE))
A11: 234 | B11: MECANICO DIESEL | C11: 1671 | D11: LÓPEZ RUBIO ENRIQUE | E11: TALLER AUTOMOTRIZ | F11: LORE601113HDFPBN05 | M11: =IF(N11="","",VLOOKUP(N11,'CURSOS 2025'!$A$3:$D$199,3,FALSE)) | Q11: =IF(N11="","",VLOOKUP(N11,'CURSOS 2025'!$A$3:$D$199,4,FALSE)) | R11: M | S11: =IF(N11="","",VLOOKUP(N11,'CURSOS 2025'!$A$3:$B$199,2,FALSE))
A12: 615 | B12: OPERADOR DE SERVICIOS B | C12: 62025 | D12: MIRANDA ALCÁNTARA DANIELA KARINA | E12: ATENCIÓN Y SERVICIOS A CONCESIONARIOS | F12: MIAD010628MDFRLNA2 | M12: =IF(N12="","",VLOOKUP(N12,'CURSOS 2025'!$A$3:$D$199,3,FALSE)) | Q12: =IF(N12="","",VLOOKUP(N12,'CURSOS 2025'!$A$3:$D$199,4,FALSE)) | R12: F | S12: =IF(N12="","",VLOOKUP(N12,'CURSOS 2025'!$A$3:$B$199,2,FALSE))
A13: 247 | B13: COSTEADOR DE ORDENES DE TRABAJO | C13: 5933 | D13: BASURTO GUZMÁN RICARDO | E13: ADMINISTRACIÓN OPERATIVA DEL PADRON | F13: BAGR630804HDFSZC07 | M13: =IF(N13="","",VLOOKUP(N13,'CURSOS 2025'!$A$3:$D$199,3,FALSE)) | Q13: =IF(N13="","",VLOOKUP(N13,'CURSOS 2025'!$A$3:$D$199,4,FALSE)) | R13: M | S13: =IF(N13="","",VLOOKUP(N13,'CURSOS 2025'!$A$3:$B$199,2,FALSE))
A14: 247 | B14: AUXILIAR ADMINISTRATIVO | C14: 555 | D14: HERNÁNDEZ MENDEZ MARIA ISABEL | E14: ADMINISTRACIÓN OPERATIVA DEL PADRON | F14: HEMI720223MOCRNS09 | M14: =IF(N14="","",VLOOKUP(N14,'CURSOS 2025'!$A$3:$D$199,3,FALSE)) | Q14: =IF(N14="","",VLOOKUP(N14,'CURSOS 2025'!$A$3:$D$199,4,FALSE)) | R14: F | S14: =IF(N14="","",VLOOKUP(N14,'CURSOS 2025'!$A$3:$B$199,2,FALSE))
A15: 247 | B15: AUXILIAR ADMINISTRATIVO | C15: 6118 | D15: SÀNCHEZ ARELLANO PABLO | E15: COORDINACIÓN ACTUALIZACIÓN DEL PADRON | F15: SAAP950220HMCNRB03 | M15: =IF(N15="","",VLOOKUP(N15,'CURSOS 2025'!$A$3:$D$199,3,FALSE)) | Q15: =IF(N15="","",VLOOKUP(N15,'CURSOS 2025'!$A$3:$D$199,4,FALSE)) | R15: M | S15: =IF(N15="","",VLOOKUP(N15,'CURSOS 2025'!$A$3:$B$199,2,FALSE))
A16: 247 | B16: CORDINADORA | C16: 20548 | D16: CORREA PIMENTEL ANA MARTHA | E16: CORDINADORA PADRÓN | F16: COPA520110MDFRMN02 | M16: =IF(N16="","",VLOOKUP(N16,'CURSOS 2025'!$A$3:$D$199,3,FALSE)) | Q16: =IF(N16="","",VLOOKUP(N16,'CURSOS 2025'!$A$3:$D$199,4,FALSE)) | R16: F | S16: =IF(N16="","",VLOOKUP(N16,'CURSOS 2025'!$A$3:$B$199,2,FALSE))
A17: 247 | B17: AUXILIAR ADMINISTRATIVO | C17: 5953 | D17: PACHECO MORALES JULIO CESAR | E17: COORDINACIÓN ACTUALIZACIÓN DEL PADRON | F17: PAMJ850601HMCCRL06 | M17: =IF(N17="","",VLOOKUP(N17,'CURSOS 2025'!$A$3:$D$199,3,FALSE)) | Q17: =IF(N17="","",VLOOKUP(N17,'CURSOS 2025'!$A$3:$D$199,4,FALSE)) | R17: M | S17: =IF(N17="","",VLOOKUP(N17,'CURSOS 2025'!$A$3:$B$199,2,FALSE))
A18: 248 | B18: PROMOTOR SOCIAL | C18: 206101 | D18: MIRANDA VICENTE GREYCE IVVANOVA | E18: COORDINACIÓN TLALNEPANTLA SECTOR I | F18: MIVG881227MDFRCR12 | M18: =IF(N18="","",VLOOKUP(N18,'CURSOS 2025'!$A$3:$D$199,3,FALSE)) | Q18: =IF(N18="","",VLOOKUP(N18,'CURSOS 2025'!$A$3:$D$199,4,FALSE)) | R18: F | S18: =IF(N18="","",VLOOKUP(N18,'CURSOS 2025'!$A$3:$B$199,2,FALSE))
A19: 248 | B19: PROMOTOR SOCIAL | C19: 20891 | D19: NUÑEZ HERNÁNDEZ MIRNA IRAIS | E19: COORDINACIÓN TLALNEPANTLA SECTOR I | F19: NUHM591120MDFXRR04 | M19: =IF(N19="","",VLOOKUP(N19,'CURSOS 2025'!$A$3:$D$199,3,FALSE)) | Q19: =IF(N19="","",VLOOKUP(N19,'CURSOS 2025'!$A$3:$D$199,4,FALSE)) | R19: F | S19: =IF(N19="","",VLOOKUP(N19,'CURSOS 2025'!$A$3:$B$199,2,FALSE))
A20: 248 | B20: PROMOTOR SOCIAL | C20: 20440 | D20: MEJIA GARCÍA FRANCISCO | E20: COORDINACIÓN TLALNEPANTLA DECTOR I | M20: =IF(N20="","",VLOOKUP(N20,'CURSOS 2025'!$A$3:$D$199,3,FALSE)) | Q20: =IF(N20="","",VLOOKUP(N20,'CURSOS 2025'!$A$3:$D$199,4,FALSE)) | R20: M | S20: =IF(N20="","",VLOOKUP(N20,'CURSOS 2025'!$A$3:$B$199,2,FALSE))
A21: 248 | B21: COORDINADOR DE SECTOR OPERATIVO | C21: 20344 | D21: HERNÁNDEZ LOYOLA JORGE | E21: COORDINACIÓN TLALNEPANTLA SECTOR II | F21: HELJ540423HOCRYR05 | M21: =IF(N21="","",VLOOKUP(N21,'CURSOS 2025'!$A$3:$D$199,3,FALSE)) | Q21: =IF(N21="","",VLOOKUP(N21,'CURSOS 2025'!$A$3:$D$199,4,FALSE)) | R21: M | S21: =IF(N21="","",VLOOKUP(N21,'CURSOS 2025'!$A$3:$B$199,2,FALSE))
A22: 248 | B22: SUPERVISOR OPERATIVO | C22: 20214 | D22: FLORES CAMPOS CARLOS JAIME | E22: COORDINACIÓN TLALNEPANTLA SECTOR II | F22: FOCC550411HDFLMR01 | M22: =IF(N22="","",VLOOKUP(N22,'CURSOS 2025'!$A$3:$D$199,3,FALSE)) | Q22: =IF(N22="","",VLOOKUP(N22,'CURSOS 2025'!$A$3:$D$199,4,FALSE)) | R22: M | S22: =IF(N22="","",VLOOKUP(N22,'CURSOS 2025'!$A$3:$B$199,2,FALSE))
A23: 248 | B23: PROMOTOR SOCIAL | C23: 20812 | D23: LÓPEZ SÁNCHEZ DORA GUADALUPE | E23: COORDINACIÓN TLALNEPANTLA SECTOR III | F23: LOSD571211MDFPNR01 | M23: =IF(N23="","",VLOOKUP(N23,'CURSOS 2025'!$A$3:$D$199,3,FALSE)) | Q23: =IF(N23="","",VLOOKUP(N23,'CURSOS 2025'!$A$3:$D$199,4,FALSE)) | R23: F | S23: =IF(N23="","",VLOOKUP(N23,'CURSOS 2025'!$A$3:$B$199,2,FALSE))
A24: 227 | B24: JEFE DE UNIDAD | C24: 206191 | D24: ANAYA VAZQUEZ CESAR | E24: DISTRIBUCIÓN | F24: AAVC751104HDFNZS03 | M24: =IF(N24="","",VLOOKUP(N24,'CURSOS 2025'!$A$3:$D$199,3,FALSE)) | Q24: =IF(N24="","",VLOOKUP(N24,'CURSOS 2025'!$A$3:$D$199,4,FALSE)) | R24: M | S24: =IF(N24="","",VLOOKUP(N24,'CURSOS 2025'!$A$3:$B$199,2,FALSE))
A25: 227 | B25: AYUDANTE GENERAL | C25: 3910 | D25: VAZQUEZ NAVARRO JUAN CARLOS | E25: DISTRIBUCIÓN | F25: VANJ700120HDFZVN08 | M25: =IF(N25="","",VLOOKUP(N25,'CURSOS 2025'!$A$3:$D$199,3,FALSE)) | Q25: =IF(N25="","",VLOOKUP(N25,'CURSOS 2025'!$A$3:$D$199,4,FALSE)) | R25: M | S25: =IF(N25="","",VLOOKUP(N25,'CURSOS 2025'!$A$3:$B$199,2,FALSE))
A26: 227 | B26: DESPACHADOR ANDEN | C26: 3652 | D26: LÓPEZ HERNÁNDEZ LAZARO | E26: COORDINACIÓN DE ATENCIÓN A TRANSPORTISTAS Y CONC. | F26: LOHL820504HCSPRZ07 | M26: =IF(N26="","",VLOOKUP(N26,'CURSOS 2025'!$A$3:$D$199,3,FALSE)) | Q26: =IF(N26="","",VLOOKUP(N26,'CURSOS 2025'!$A$3:$D$199,4,FALSE)) | R26: M | S26: =IF(N26="","",VLOOKUP(N26,'CURSOS 2025'!$A$3:$B$199,2,FALSE))
A27: 233 | B27: SUPERVISOR DE DISTRIBUCION EN CAMPO | C27: 1403 | D27: HERNÁNDEZ MENDOZA JOSÉ GUADALUPE | E27: DISTRIBUCIÓN | F27: HEMG650228HMCRND08 | M27: =IF(N27="","",VLOOKUP(N27,'CURSOS 2025'!$A$3:$D$199,3,FALSE)) | Q27: =IF(N27="","",VLOOKUP(N27,'CURSOS 2025'!$A$3:$D$199,4,FALSE)) | R27: M | S27: =IF(N27="","",VLOOKUP(N27,'CURSOS 2025'!$A$3:$B$199,2,FALSE))
A28: 233 | B28: SUPERVISOR DE DISTRIBUCION EN CAMPO | C28: 20325 | D28: VITAL LAZARO ARTURO | E28: COORDINACIÓN DISTRIBUCIÓN SECTOR I | F28: VILA571215HMSTZR00 | M28: =IF(N28="","",VLOOKUP(N28,'CURSOS 2025'!$A$3:$D$199,3,FALSE)) | Q28: =IF(N28="","",VLOOKUP(N28,'CURSOS 2025'!$A$3:$D$199,4,FALSE)) | R28: M | S28: =IF(N28="","",VLOOKUP(N28,'CURSOS 2025'!$A$3:$B$199,2,FALSE))
A29: 228 | B29: SUPERVISOR DE CONTROL DE PARQUE VEHICULAR | C29: 20876 | D29: GARCÍA PARRALES JOSÉ DE JESUS | E29: MANTENIMIENTO CIVIL A LECHERIAS | F29: GAPJ540513HDFRRS01 | M29: =IF(N29="","",VLOOKUP(N29,'CURSOS 2025'!$A$3:$D$199,3,FALSE)) | Q29: =IF(N29="","",VLOOKUP(N29,'CURSOS 2025'!$A$3:$D$199,4,FALSE)) | R29: M | S29: =IF(N29="","",VLOOKUP(N29,'CURSOS 2025'!$A$3:$B$199,2,FALSE))
A30: 228 | B30: TECNICO EN MANTENIMIENTO | C30: 1925 | D30: DE LA ROSA ALEGRIA FLORENCIO | E30: COORDINACIÓN DE MANTENIMIENTO CIVIL REGIÓN I | F30: ROAF611029 HOCSLL01 | M30: =IF(N30="","",VLOOKUP(N30,'CURSOS 2025'!$A$3:$D$199,3,FALSE)) | Q30: =IF(N30="","",VLOOKUP(N30,'CURSOS 2025'!$A$3:$D$199,4,FALSE)) | R30: M | S30: =IF(N30="","",VLOOKUP(N30,'CURSOS 2025'!$A$3:$B$199,2,FALSE))
A31: 228 | B31: TECNICO EN MANTENIMIENTO | C31: 1552 | D31: PÉREZ HERNÁNDEZ JOSÉ GUADALUPE | E31: COORDINACIÓN DE MANTENIMIENTO CIVIL REGIÓN I | F31: PEHG661209 HMCRRD02 | M31: =IF(N31="","",VLOOKUP(N31,'CURSOS 2025'!$A$3:$D$199,3,FALSE)) | Q31: =IF(N31="","",VLOOKUP(N31,'CURSOS 2025'!$A$3:$D$199,4,FALSE)) | R31: M | S31: =IF(N31="","",VLOOKUP(N31,'CURSOS 2025'!$A$3:$B$199,2,FALSE))
A32: 228 | B32: ALBAÑIL | C32: 3548 | D32: PRIETO OSORNIO ALEJANDRO | E32: COORDINACIÓN DE MANTENIMIENTO CIVIL REGIÓN I | F32: PIOA590221HDFRSL02 | M32: =IF(N32="","",VLOOKUP(N32,'CURSOS 2025'!$A$3:$D$199,3,FALSE)) | Q32: =IF(N32="","",VLOOKUP(N32,'CURSOS 2025'!$A$3:$D$199,4,FALSE)) | R32: M | S32: =IF(N32="","",VLOOKUP(N32,'CURSOS 2025'!$A$3:$B$199,2,FALSE))
... A43: 328 | B43: AYUDANTE ESPECIALIZADO | C43: 3907 | D43: PADRÓN VAZQUEZ JORGE MANUEL | E43: PRODUCCIÓN | F43: PAVJ810816HDFDZR08 | M43: =IF(N43="","",VLOOKUP(N43,'CURSOS 2025'!$A$3:$D$199,3,FALSE)) | Q43: =IF(N43="","",VLOOKUP(N43,'CURSOS 2025'!$A$3:$D$199,4,FALSE)) | R43: M | S43: =IF(N43="","",VLOOKUP(N43,'CURSOS 2025'!$A$3:$B$199,2,FALSE))
A44: 329 | B44: MECÁNICO SUSPENSIÓN | C44: 3800 | D44: TREJO CORREA RENE | E44: TALLER AUTOMOTRIZ | F44: TECR920715HDFRRN08 | J44: X | K44: X | L44: X | M44: =IF(N44="","",VLOOKUP(N44,'CURSOS 2025'!$A$3:$D$199,3,FALSE)) -> #N/A | N44: HOJALATERIA Y PINTURA | O44: 45334 | P44: 45338 | Q44: =IF(N44="","",VLOOKUP(N44,'CURSOS 2025'!$A$3:$D$199,4,FALSE)) -> #N/A | R44: M | S44: =IF(N44="","",VLOOKUP(N44,'CURSOS 2025'!$A$3:$B$199,2,FALSE)) -> #N/A
A45: 328 | B45: OPERADOR DE MAQUINA | C45: 3505 | D45: GONZÁLEZ REYES IVAN | E45: PRODUCCIÓN | F45: GORI811230HDFNYV02 | M45: =IF(N45="","",VLOOKUP(N45,'CURSOS 2025'!$A$3:$D$199,3,FALSE)) | Q45: =IF(N45="","",VLOOKUP(N45,'CURSOS 2025'!$A$3:$D$199,4,FALSE)) | R45: M | S45: =IF(N45="","",VLOOKUP(N45,'CURSOS 2025'!$A$3:$B$199,2,FALSE))
A46: 328 | B46: OPERADOR DE REHIDRATADO | C46: 3707 | D46: DURAN GÓMEZ LEONARDO | E46: PRODUCCIÓN | F46: DUGL581015HVZRMN04 | M46: =IF(N46="","",VLOOKUP(N46,'CURSOS 2025'!$A$3:$D$199,3,FALSE)) | Q46: =IF(N46="","",VLOOKUP(N46,'CURSOS 2025'!$A$3:$D$199,4,FALSE)) | R46: M | S46: =IF(N46="","",VLOOKUP(N46,'CURSOS 2025'!$A$3:$B$199,2,FALSE))
A47: 328 | B47: OPERADOR DE MAQUINA | C47: 1262 | D47: TETELPA CARIÑO TEODULO | E47: PRODUCCIÓN | F47: TECT630217HVZTRD05 | M47: =IF(N47="","",VLOOKUP(N47,'CURSOS 2025'!$A$3:$D$199,3,FALSE)) | Q47: =IF(N47="","",VLOOKUP(N47,'CURSOS 2025'!$A$3:$D$199,4,FALSE)) | R47: M | S47: =IF(N47="","",VLOOKUP(N47,'CURSOS 2025'!$A$3:$B$199,2,FALSE))
A48: 328 | B48: AYUDANTE GENERAL | C48: 3977 | D48: CISNEROS FLORES GABRIEL | E48: PRODUCCIÓN | F48: CIFG920405HMCSLB03 | M48: =IF(N48="","",VLOOKUP(N48,'CURSOS 2025'!$A$3:$D$199,3,FALSE)) | Q48: =IF(N48="","",VLOOKUP(N48,'CURSOS 2025'!$A$3:$D$199,4,FALSE)) | R48: M | S48: =IF(N48="","",VLOOKUP(N48,'CURSOS 2025'!$A$3:$B$199,2,FALSE))
A49: 328 | B49: AYUDANTE GENERAL | C49: 3995 | D49: DURAN RODRÍGUEZ ANDRES ARIEL | E49: PRODUCCIÓN | F49: DURA031227HDFRDNA7 | M49: =IF(N49="","",VLOOKUP(N49,'CURSOS 2025'!$A$3:$D$199,3,FALSE)) | Q49: =IF(N49="","",VLOOKUP(N49,'CURSOS 2025'!$A$3:$D$199,4,FALSE)) | R49: M | S49: =IF(N49="","",VLOOKUP(N49,'CURSOS 2025'!$A$3:$B$199,2,FALSE))
A50: 328 | B50: AYUDANTE GENERAL | C50: 1996 | D50: ENSALDO SEGURA HERIBERTO | E50: PRODUCCIÓN | F50: EASH730810HDFNGR04 | M50: =IF(N50="","",VLOOKUP(N50,'CURSOS 2025'!$A$3:$D$199,3,FALSE)) | Q50: =IF(N50="","",VLOOKUP(N50,'CURSOS 2025'!$A$3:$D$199,4,FALSE)) | R50: M | S50: =IF(N50="","",VLOOKUP(N50,'CURSOS 2025'!$A$3:$B$199,2,FALSE))
A51: 336 | B51: COORDINADOR | C51: 20259 | D51: RAMÍREZ SÁNCHEZ ANTONIO | E51: MANTENIMIENTO A PLANTA | F51: RASA611107HHGMNN09 | M51: =IF(N51="","",VLOOKUP(N51,'CURSOS 2025'!$A$3:$D$199,3,FALSE)) | Q51: =IF(N51="","",VLOOKUP(N51,'CURSOS 2025'!$A$3:$D$199,4,FALSE)) | R51: M | S51: =IF(N51="","",VLOOKUP(N51,'CURSOS 2025'!$A$3:$B$199,2,FALSE))
A52: 336 | B52: AYUDANTE GENERAL | C52: 3956 | D52: FLORENCIO BARRERA OSCAR IVÁN | E52: MANTENIMIENTO A PLANTA | F52: FOBO000703HMCLRSA4 | M52: =IF(N52="","",VLOOKUP(N52,'CURSOS 2025'!$A$3:$D$199,3,FALSE)) | Q52: =IF(N52="","",VLOOKUP(N52,'CURSOS 2025'!$A$3:$D$199,4,FALSE)) | R52: M | S52: =IF(N52="","",VLOOKUP(N52,'CURSOS 2025'!$A$3:$B$199,2,FALSE))
A53: 336 | B53: MECÁNICO "A" | C53: 3764 | D53: GARCÍA TEJERA ISRAEL | E53: MANTENIMIENTO A PLANTA | F53: GATI820506HDFRJS05 | M53: =IF(N53="","",VLOOKUP(N53,'CURSOS 2025'!$A$3:$D$199,3,FALSE)) | Q53: =IF(N53="","",VLOOKUP(N53,'CURSOS 2025'!$A$3:$D$199,4,FALSE)) | R53: M | S53: =IF(N53="","",VLOOKUP(N53,'CURSOS 2025'!$A$3:$B$199,2,FALSE))
A54: 336 | B54: AYUDANTE ESPECIALIZADO | C54: 3869 | D54: CEBALLOS NAVARRETE ARTURO | E54: MANTENIMIENTO A PLANTA | F54: CENA620317HMSBVR01 | M54: =IF(N54="","",VLOOKUP(N54,'CURSOS 2025'!$A$3:$D$199,3,FALSE)) | Q54: =IF(N54="","",VLOOKUP(N54,'CURSOS 2025'!$A$3:$D$199,4,FALSE)) | R54: M | S54: =IF(N54="","",VLOOKUP(N54,'CURSOS 2025'!$A$3:$B$199,2,FALSE))
A55: 336 | B55: MECANICO "A" | C55: 1792 | D55: PÉREZ SAENZ HERMENEGILDO | E55: MANTENIMIENTO A PLANTA | F55: UASL650311HMCGLS09 | M55: =IF(N55="","",VLOOKUP(N55,'CURSOS 2025'!$A$3:$D$199,3,FALSE)) | Q55: =IF(N55="","",VLOOKUP(N55,'CURSOS 2025'!$A$3:$D$199,4,FALSE)) | R55: M | S55: =IF(N55="","",VLOOKUP(N55,'CURSOS 2025'!$A$3:$B$199,2,FALSE))
A56: 336 | B56: ELECTRICISTA "B" | C56: 3394 | D56: PINEDA LÓPEZ JULIAN GUADALUPE | E56: MANTENIMIENTO A PLANTA | F56: PILJ710109HDFNPL03 | M56: =IF(N56="","",VLOOKUP(N56,'CURSOS 2025'!$A$3:$D$199,3,FALSE)) | Q56: =IF(N56="","",VLOOKUP(N56,'CURSOS 2025'!$A$3:$D$199,4,FALSE)) | R56: M | S56: =IF(N56="","",VLOOKUP(N56,'CURSOS 2025'!$A$3:$B$199,2,FALSE))
A57: 336 | B57: OPERADOR DE TRATAMIENTO DE AGUA | C57: 3095 | D57: CALVA ESCAMILLA LORENZO EDUARDO | E57: MANTENIMIENTO A PLANTA | F57: CAEL620810HPLLSR08 | M57: =IF(N57="","",VLOOKUP(N57,'CURSOS 2025'!$A$3:$D$199,3,FALSE)) | Q57: =IF(N57="","",VLOOKUP(N57,'CURSOS 2025'!$A$3:$D$199,4,FALSE)) | R57: M | S57: =IF(N57="","",VLOOKUP(N57,'CURSOS 2025'!$A$3:$B$199,2,FALSE))
A58: 810 | B58: JEFE DE OFICINA | C58: 205902 | D58: GONZÁLEZ RODRÍGUEZ MARIA DE JESUS | E58: SUB. DE ADMINISTRACIÓN Y FINANZAS | F58: GORJ631030MDFNDS16 | M58: =IF(N58="","",VLOOKUP(N58,'CURSOS 2025'!$A$3:$D$199,3,FALSE)) | Q58: =IF(N58="","",VLOOKUP(N58,'CURSOS 2025'!$A$3:$D$199,4,FALSE)) | R58: F | S58: =IF(N58="","",VLOOKUP(N58,'CURSOS 2025'!$A$3:$B$199,2,FALSE))
A59: 810 | B59: AUXILIAR PROYECTO "E" | C59: 62017 | D59: TAVERA VILLALPANDO MANUEL ROBERTO | E59: SUB. DE ADMINISTRACIÓN Y FINANZAS | F59: TAVM860509HDFVLN02 | M59: =IF(N59="","",VLOOKUP(N59,'CURSOS 2025'!$A$3:$D$199,3,FALSE)) | Q59: =IF(N59="","",VLOOKUP(N59,'CURSOS 2025'!$A$3:$D$199,4,FALSE)) | R59: M | S59: =IF(N59="","",VLOOKUP(N59,'CURSOS 2025'!$A$3:$B$199,2,FALSE))
A60: 846 | B60: COORDINADOR GENERAL | C60: 20469 | D60: PINEDA PINEDA JAVIER | E60: RELACIONES INDUSTRIALES | F60: PIPJ660806HGRNNV02 | M60: =IF(N60="","",VLOOKUP(N60,'CURSOS 2025'!$A$3:$D$199,3,FALSE)) | Q60: =IF(N60="","",VLOOKUP(N60,'CURSOS 2025'!$A$3:$D$199,4,FALSE)) | R60: M | S60: =IF(N60="","",VLOOKUP(N60,'CURSOS 2025'!$A$3:$B$199,2,FALSE))
A61: 846 | B61: MÈDICO | C61: 206263 | D61: GUADARRAMA FERNANDEZ DE LARA SALVADOR | E61: RELACIONES INDUSTRIALES | F61: GUFS920728HDFDRL02 | M61: =IF(N61="","",VLOOKUP(N61,'CURSOS 2025'!$A$3:$D$199,3,FALSE)) | Q61: =IF(N61="","",VLOOKUP(N61,'CURSOS 2025'!$A$3:$D$199,4,FALSE)) | R61: M | S61: =IF(N61="","",VLOOKUP(N61,'CURSOS 2025'!$A$3:$B$199,2,FALSE))
A62: 846 | B62: SUPERVISOR | C62: 206274 | D62: ROMERO ALVAREZ OSWALDO | E62: RELACIONES INDUSTRIALES | F62: ROAO920520HMCMLS06 | M62: =IF(N62="","",VLOOKUP(N62,'CURSOS 2025'!$A$3:$D$199,3,FALSE)) | Q62: =IF(N62="","",VLOOKUP(N62,'CURSOS 2025'!$A$3:$D$199,4,FALSE)) | R62: M | S62: =IF(N62="","",VLOOKUP(N62,'CURSOS 2025'!$A$3:$B$199,2,FALSE))
A63: 846 | B63: JEFE DE UNIDAD | C63: 206276 | D63: DIAZ RODRIGUEZ MARIA FERNANDA | E63: RELACIONES INDUSTRIALES | F63: DIRF880325MDFZDR00 | M63: =IF(N63="","",VLOOKUP(N63,'CURSOS 2025'!$A$3:$D$199,3,FALSE)) | Q63: =IF(N63="","",VLOOKUP(N63,'CURSOS 2025'!$A$3:$D$199,4,FALSE)) | R63: F | S63: =IF(N63="","",VLOOKUP(N63,'CURSOS 2025'!$A$3:$B$199,2,FALSE))
A64: 846 | B64: ANALISTA DE PROYECTO E | C64: 62022 | D64: HURTADO GARCIA JOSE ALFREDO | E64: RELACIONES INDUSTRIALES | F64: HUGA670522HDFRRL01 | M64: =IF(N64="","",VLOOKUP(N64,'CURSOS 2025'!$A$3:$D$199,3,FALSE)) | Q64: =IF(N64="","",VLOOKUP(N64,'CURSOS 2025'!$A$3:$D$199,4,FALSE)) | R64: M | S64: =IF(N64="","",VLOOKUP(N64,'CURSOS 2025'!$A$3:$B$199,2,FALSE))
A65: 846 | B65: JEFE DE UNIDAD | C65: 206234 | D65: CUEVAS IZQUIERDO MAURICIO | E65: COORDINACIÓN SEGURIDAD E HIGIENE | F65: CUIM850418HDFVZR01 | M65: =IF(N65="","",VLOOKUP(N65,'CURSOS 2025'!$A$3:$D$199,3,FALSE)) | Q65: =IF(N65="","",VLOOKUP(N65,'CURSOS 2025'!$A$3:$D$199,4,FALSE)) | R65: F | S65: =IF(N65="","",VLOOKUP(N65,'CURSOS 2025'!$A$3:$B$199,2,FALSE))
A66: 625 | B66: JEFE DE OFICINA | C66: 205393 | D66: GONZÁLEZ ROBLEDO LUCIA | E66: FINANZAS | F66: GORL750322MMCNBC03 | M66: =IF(N66="","",VLOOKUP(N66,'CURSOS 2025'!$A$3:$D$199,3,FALSE)) | Q66: =IF(N66="","",VLOOKUP(N66,'CURSOS 2025'!$A$3:$D$199,4,FALSE)) | R66: F | S66: =IF(N66="","",VLOOKUP(N66,'CURSOS 2025'!$A$3:$B$199,2,FALSE))
A67: 625 | B67: JEFE DE UNIDAD | C67: 205520 | D67: LÓPEZ LÓPEZ RICARDO | E67: FINANZAS | F67: LOLR690207HMCPPC03 | M67: =IF(N67="","",VLOOKUP(N67,'CURSOS 2025'!$A$3:$D$199,3,FALSE)) | Q67: =IF(N67="","",VLOOKUP(N67,'CURSOS 2025'!$A$3:$D$199,4,FALSE)) | R67: M | S67: =IF(N67="","",VLOOKUP(N67,'CURSOS 2025'!$A$3:$B$199,2,FALSE))
A68: 625 | B68: JEFE DE OFICINA | C68: 205396 | D68: CHAMORRO SÁNCHEZ FRANCISCO EDUARDO | E68: FINANZAS | F68: CASF611012HMCHNR05 | M68: =IF(N68="","",VLOOKUP(N68,'CURSOS 2025'!$A$3:$D$199,3,FALSE)) | Q68: =IF(N68="","",VLOOKUP(N68,'CURSOS 2025'!$A$3:$D$199,4,FALSE)) | R68: M | S68: =IF(N68="","",VLOOKUP(N68,'CURSOS 2025'!$A$3:$B$199,2,FALSE))
A69: 347 | B69: JEFE DE UNIDAD | C69: 206232 | D69: HERRERA VIEYRA GERMÁN | E69: ALMACENES | F69: HEVG630528HDFRYR03 | M69: =IF(N69="","",VLOOKUP(N69,'CURSOS 2025'!$A$3:$D$199,3,FALSE)) | Q69: =IF(N69="","",VLOOKUP(N69,'CURSOS 2025'!$A$3:$D$199,4,FALSE)) | R69: M | S69: =IF(N69="","",VLOOKUP(N69,'CURSOS 2025'!$A$3:$B$199,2,FALSE))
A70: 345 | B70: JEFE DE OFICINA | C70: 205950 | D70: VARGAS GARCÍA JOSÉ RAMÓN | E70: ALMACENES | F70: VAGR871207HDFRRM03 | M70: =IF(N70="","",VLOOKUP(N70,'CURSOS 2025'!$A$3:$D$199,3,FALSE)) | Q70: =IF(N70="","",VLOOKUP(N70,'CURSOS 2025'!$A$3:$D$199,4,FALSE)) | R70: M | S70: =IF(N70="","",VLOOKUP(N70,'CURSOS 2025'!$A$3:$B$199,2,FALSE))
A71: 347 | B71: AUXILIAR ADMINISTRATIVO | C71: 6058 | D71: VILLEGAS ROBLES JORGE | E71: ADMINISTRACIÓN OPERATIVA DEL PADRON | F71: VIRJ590114HDFLBR01 | M71: =IF(N71="","",VLOOKUP(N71,'CURSOS 2025'!$A$3:$D$199,3,FALSE)) | Q71: =IF(N71="","",VLOOKUP(N71,'CURSOS 2025'!$A$3:$D$199,4,FALSE)) | R71: M | S71: =IF(N71="","",VLOOKUP(N71,'CURSOS 2025'!$A$3:$B$199,2,FALSE))
A72: 347 | B72: AUXILIAR ADMINISTRATIVO | C72: 311 | D72: RODRÍGUEZ RODRÍGUEZ PATRICIA | E72: ALMACENES | F72: RORP640606MDFDDT03 | M72: =IF(N72="","",VLOOKUP(N72,'CURSOS 2025'!$A$3:$D$199,3,FALSE)) | Q72: =IF(N72="","",VLOOKUP(N72,'CURSOS 2025'!$A$3:$D$199,4,FALSE)) | R72: F | S72: =IF(N72="","",VLOOKUP(N72,'CURSOS 2025'!$A$3:$B$199,2,FALSE))
A73: 347 | B73: ALMACENISTA A | C73: 3470 | D73: PANIAGUA VEGA JOSÉ LUIS | E73: ALMACENES | F73: PAVL631203HMCNGS03 | M73: =IF(N73="","",VLOOKUP(N73,'CURSOS 2025'!$A$3:$D$199,3,FALSE)) | Q73: =IF(N73="","",VLOOKUP(N73,'CURSOS 2025'!$A$3:$D$199,4,FALSE)) | R73: M | S73: =IF(N73="","",VLOOKUP(N73,'CURSOS 2025'!$A$3:$B$199,2,FALSE))
A74: 329 | B74: ALMACENISTA A | C74: 3669 | D74: HERNÁNDEZ LÓPEZ ERICK OMAR | E74: ALMACENES | F74: HELE760717HDFRPR09 | M74: =IF(N74="","",VLOOKUP(N74,'CURSOS 2025'!$A$3:$D$199,3,FALSE)) | Q74: =IF(N74="","",VLOOKUP(N74,'CURSOS 2025'!$A$3:$D$199,4,FALSE)) | R74: M | S74: =IF(N74="","",VLOOKUP(N74,'CURSOS 2025'!$A$3:$B$199,2,FALSE))
A75: 346 | B75: MONTACARGUISTA | C75: 1567 | D75: TREJO DEL VALLE PORFIRIO | E75: ALMACENES | F75: TEVP620915HMCRLR06 | M75: =IF(N75="","",VLOOKUP(N75,'CURSOS 2025'!$A$3:$D$199,3,FALSE)) | Q75: =IF(N75="","",VLOOKUP(N75,'CURSOS 2025'!$A$3:$D$199,4,FALSE)) | R75: M | S75: =IF(N75="","",VLOOKUP(N75,'CURSOS 2025'!$A$3:$B$199,2,FALSE))
A76: 347 | B76: MONTACARGUISTA | C76: 1228 | D76: CORTES LIRA RAUL | E76: ALMACENES | F76: COLR630611HDFRRL03 | M76: =IF(N76="","",VLOOKUP(N76,'CURSOS 2025'!$A$3:$D$199,3,FALSE)) | Q76: =IF(N76="","",VLOOKUP(N76,'CURSOS 2025'!$A$3:$D$199,4,FALSE)) | R76: M | S76: =IF(N76="","",VLOOKUP(N76,'CURSOS 2025'!$A$3:$B$199,2,FALSE))
A77: 915 | B77: COORDINADOR GENERAL | C77: 205100 | D77: DOMINGUEZ NARANJO JOSÉ LUIS | E77: ADQUISICIONES Y SERVICIOS GENERALES | F77: DONL620105HDFMRS06 | M77: =IF(N77="","",VLOOKUP(N77,'CURSOS 2025'!$A$3:$D$199,3,FALSE)) | Q77: =IF(N77="","",VLOOKUP(N77,'CURSOS 2025'!$A$3:$D$199,4,FALSE)) | R77: M | S77: =IF(N77="","",VLOOKUP(N77,'CURSOS 2025'!$A$3:$B$199,2,FALSE))
A78: 915 | B78: ANALISTA | C78: 206271 | D78: CALDERON GARDUÑO ANAYELI | E78: ADQUISICIONES Y SERVICIOS GENERALES | F78: CXJA000220MMCLRNA0 | M78: =IF(N78="","",VLOOKUP(N78,'CURSOS 2025'!$A$3:$D$199,3,FALSE)) | Q78: =IF(N78="","",VLOOKUP(N78,'CURSOS 2025'!$A$3:$D$199,4,FALSE)) | R78: F | S78: =IF(N78="","",VLOOKUP(N78,'CURSOS 2025'!$A$3:$B$199,2,FALSE))
A79: 915 | B79: ANALISTA DE PROYECTO F | C79: 22063 | D79: MORENO GOMEZ RICARDO | E79: ADQUISICIONES Y SERVICIOS GENERALES | F79: GOMR800919HMCMRC03 | M79: =IF(N79="","",VLOOKUP(N79,'CURSOS 2025'!$A$3:$D$199,3,FALSE)) | Q79: =IF(N79="","",VLOOKUP(N79,'CURSOS 2025'!$A$3:$D$199,4,FALSE)) | R79: M | S79: =IF(N79="","",VLOOKUP(N79,'CURSOS 2025'!$A$3:$B$199,2,FALSE))
A80: 915 | B80: JEFE DE UNIDAD | C80: 206045 | D80: NIETO DAVALOS MIGUEL ÁNGEL | E80: COORDINACIÓN ADQUSICIONES | F80: NIDM860705HDFTVG07 | M80: =IF(N80="","",VLOOKUP(N80,'CURSOS 2025'!$A$3:$D$199,3,FALSE)) | Q80: =IF(N80="","",VLOOKUP(N80,'CURSOS 2025'!$A$3:$D$199,4,FALSE)) | R80: F | S80: =IF(N80="","",VLOOKUP(N80,'CURSOS 2025'!$A$3:$B$199,2,FALSE))
A81: 915 | B81: JEFE DE UNIDAD | C81: 5105 | D81: ALAMILLA CORTES ERICK ALEJANDRO | E81: RECURSOS MATERIALES | F81: AACE740205HDFLRR03 | M81: =IF(N81="","",VLOOKUP(N81,'CURSOS 2025'!$A$3:$D$199,3,FALSE)) | Q81: =IF(N81="","",VLOOKUP(N81,'CURSOS 2025'!$A$3:$D$199,4,FALSE)) | R81: M | S81: =IF(N81="","",VLOOKUP(N81,'CURSOS 2025'!$A$3:$B$199,2,FALSE))
A82: 915 | B82: JEFE DE UNIDAD | C82: 206054 | D82: BONFANTE PINEDA STEFANY | E82: RECURSOS MATERIALES | F82: BOPS910522MMCNNT05 | M82: =IF(N82="","",VLOOKUP(N82,'CURSOS 2025'!$A$3:$D$199,3,FALSE)) | Q82: =IF(N82="","",VLOOKUP(N82,'CURSOS 2025'!$A$3:$D$199,4,FALSE)) | R82: F | S82: =IF(N82="","",VLOOKUP(N82,'CURSOS 2025'!$A$3:$B$199,2,FALSE))
A83: 915 | B83: AXILIAR ADMINISTRATIVO | C83: 205938 | D83: PÉREZ MUÑOZ MARIA JUANA | E83: RECURSOS MATERIALES | F83: PEMJ650328MHGRXN07 | M83: =IF(N83="","",VLOOKUP(N83,'CURSOS 2025'!$A$3:$D$199,3,FALSE)) | Q83: =IF(N83="","",VLOOKUP(N83,'CURSOS 2025'!$A$3:$D$199,4,FALSE)) | R83: F | S83: =IF(N83="","",VLOOKUP(N83,'CURSOS 2025'!$A$3:$B$199,2,FALSE))
A84: 915 | B84: AYUDANTE ESPECIALIZADO | C84: 3875 | D84: GARCÍA VALENZUELA JOSÉ LUIS | E84: RECURSOS MATERIALES | F84: GAVL620501HCHRLS08 | M84: =IF(N84="","",VLOOKUP(N84,'CURSOS 2025'!$A$3:$D$199,3,FALSE)) | Q84: =IF(N84="","",VLOOKUP(N84,'CURSOS 2025'!$A$3:$D$199,4,FALSE)) | R84: M | S84: =IF(N84="","",VLOOKUP(N84,'CURSOS 2025'!$A$3:$B$199,2,FALSE))
A85: 915 | B85: CHOFER | C85: 1388 | D85: NIEVES PÉREZ ANTONIO | E85: ADQUISICIONES Y SERVICIOS GENERALES | F85: NIPA630613HDFVRN00 | M85: =IF(N85="","",VLOOKUP(N85,'CURSOS 2025'!$A$3:$D$199,3,FALSE)) | Q85: =IF(N85="","",VLOOKUP(N85,'CURSOS 2025'!$A$3:$D$199,4,FALSE)) | R85: M | S85: =IF(N85="","",VLOOKUP(N85,'CURSOS 2025'!$A$3:$B$199,2,FALSE))
A86: 248 | B86: PROMOTOR SOCIAL | C86: 206204 | D86: ESPINOSA SANTA ROSA ALEJANDRO | E86: PERSONAL EVENTUAL | F86: EISA750424HDFSNL08 | M86: =IF(N86="","",VLOOKUP(N86,'CURSOS 2025'!$A$3:$D$199,3,FALSE)) | Q86: =IF(N86="","",VLOOKUP(N86,'CURSOS 2025'!$A$3:$D$199,4,FALSE)) | R86: M | S86: =IF(N86="","",VLOOKUP(N86,'CURSOS 2025'!$A$3:$B$199,2,FALSE))
A87: 248 | B87: PROMOTOR SOCIAL | C87: 206186 | D87: VEGA LARIOS MIGUEL BRANDON | E87: PERSONAL EVENTUAL | F87: VELM990929HMCGRG05 | M87: =IF(N87="","",VLOOKUP(N87,'CURSOS 2025'!$A$3:$D$199,3,FALSE)) | Q87: =IF(N87="","",VLOOKUP(N87,'CURSOS 2025'!$A$3:$D$199,4,FALSE)) | R87: M | S87: =IF(N87="","",VLOOKUP(N87,'CURSOS 2025'!$A$3:$B$199,2,FALSE))
A88: 301 | B88: OPERADOR DE SERVICIOS B | C88: 62001 | D88: AVILA MEJIA DANIEL | E88: PERSONAL POR HONORARIOS | F88: AIMD000512HMCVJNA7 | M88: =IF(N88="","",VLOOKUP(N88,'CURSOS 2025'!$A$3:$D$199,3,FALSE)) | Q88: =IF(N88="","",VLOOKUP(N88,'CURSOS 2025'!$A$3:$D$199,4,FALSE)) | R88: M | S88: =IF(N88="","",VLOOKUP(N88,'CURSOS 2025'!$A$3:$B$199,2,FALSE))
A89: 301 | B89: OPERADOR DE SERVICIOS B | C89: 62002 | D89: CARBAJAL LOPEZ ZAIRA ITZEL | E89: PERSONAL POR HONORARIOS | F89: CALZ960619MHGRPR08 | M89: =IF(N89="","",VLOOKUP(N89,'CURSOS 2025'!$A$3:$D$199,3,FALSE)) | Q89: =IF(N89="","",VLOOKUP(N89,'CURSOS 2025'!$A$3:$D$199,4,FALSE)) | R89: F | S89: =IF(N89="","",VLOOKUP(N89,'CURSOS 2025'!$A$3:$B$199,2,FALSE))
A90: 301 | B90: ANALISTA DE PROYECTO E | C90: 62007 | D90: FUENTES GRACIANO PEDRO ELMER | E90: PERSONAL POR HONORARIOS | F90: FUGP640531HDFNRD04 | M90: =IF(N90="","",VLOOKUP(N90,'CURSOS 2025'!$A$3:$D$199,3,FALSE)) | Q90: =IF(N90="","",VLOOKUP(N90,'CURSOS 2025'!$A$3:$D$199,4,FALSE)) | R90: M | S90: =IF(N90="","",VLOOKUP(N90,'CURSOS 2025'!$A$3:$B$199,2,FALSE))
A91: 301 | B91: ANALISTA DE PROYECTO E | C91: 640004 | D91: SANDOVAL RAMON JORGE | E91: PERSONAL POR HONORARIOS | F91: SARJ720225HDFNMR00 | M91: =IF(N91="","",VLOOKUP(N91,'CURSOS 2025'!$A$3:$D$199,3,FALSE)) | Q91: =IF(N91="","",VLOOKUP(N91,'CURSOS 2025'!$A$3:$D$199,4,FALSE)) | R91: M | S91: =IF(N91="","",VLOOKUP(N91,'CURSOS 2025'!$A$3:$B$199,2,FALSE))
... A95: 301 | B95: ANALISTA DE PROYECTO F | C95: 62012 | D95: OBREGÓN GONZÁLEZ GABRIEL | E95: PERSONAL POR HONORARIOS | F95: OEGG640830HDFBNB05 | M95: =IF(N95="","",VLOOKUP(N95,'CURSOS 2025'!$A$3:$D$199,3,FALSE)) | Q95: =IF(N95="","",VLOOKUP(N95,'CURSOS 2025'!$A$3:$D$199,4,FALSE)) | R95: M | S95: =IF(N95="","",VLOOKUP(N95,'CURSOS 2025'!$A$3:$B$199,2,FALSE))
